Workbook

Sheet README
A1: GCCN_5YR_Financial_Model.xlsx
A3: Sheets
A4: Assumptions — yellow INPUTS; C5 scenario toggle
A5: Annual_PnL — Y1–Y5 × Cons/Base/Upside + selected summary
A6: Monthly_Y1 — seasonality × Y1
A7: Unit_Economics — per-booking contribution
A9: Recommended model: asset-light marketplace ~12% Base (+~1.5pts owned/sister) take on GMV via owned Stripe; OTAs optional Channels only.
A11: Disclaimer: Sourced tourism = context only. Bookings/AOV/CAC/OpEx/take = ASSUMPTIONS. Pre-tax. Not investment advice.
A13: Companion: ../BUSINESS_PLAN_5YR.md | ../MARKETING_AND_SCALE.md

Sheet Assumptions
A1: GCCN 5-Year Financial Model — ASSUMPTIONS
A2: Yellow=INPUT. Tourism figures SOURCED for context only (NOT GCCN capture). Volumes/rates/costs=ASSUMPTIONS. Pre-tax USD. Stripe on PLATFORM FEE SLICE when U8=1.
A4: ID | B4: Parameter | C4: Conservative | D4: Base | E4: Upside | F4: Notes / Source
A5: SCENARIO_TOGGLE | B5: Active scenario for Annual_PnL Selected summary | C5: Base | D5: INPUT: Conservative | Base | Upside
A6: M1 | B6: Beach visitors 2024 (GSOB+FM) context | C6: 6490000 | D6: 6490000 | E6: 6490000 | F6: SOURCED Deravi/GSOBT ~6.49M — NOT capture
A7: M2 | B7: Beach visitors 2025 (GSOB+FM) context | C7: 7140000 | D7: 7140000 | E7: 7140000 | F7: SOURCED GSOBT/ATD ~7.14M — NOT capture
A8: M3 | B8: Lodging sales beaches 2025 $M context | C8: 923 | D8: 923 | E8: 923 | F8: SOURCED al.com/GSOBT ~$923M
A9: M4 | B9: Peak lodging tax share Apr-Sep | C9: 0.7 | D9: 0.7 | E9: 0.7 | F9: SOURCED ATD ~70% Apr-Sep
A10: U1 | B10: Blended AOV ($) | C10: 600 | D10: 750 | E10: 950 | F10: ASSUMPTION public price-band mix
A11: U2 | B11: Network take rate | C11: 0.1 | D11: 0.12 | E11: 0.14 | F11: ASSUMPTION 10-15% vs FH~6% / OTA 20-30% sourced
A12: U3 | B12: Owned/sister uplift on take (pts) | C12: 0.005 | D12: 0.015 | E12: 0.03 | F12: ASSUMPTION spear/owned mix
A13: U4 | B13: Effective take rate (U2+U3) | C13: =C11+C12 | D13: =D11+D12 | E13: =E11+E12 | F13: CALCULATED
A14: U5 | B14: Deposit fraction of AOV | C14: 0.3 | D14: 0.3 | E14: 0.35 | F14: ASSUMPTION
A15: U6 | B15: Stripe fee % | C15: 0.029 | D15: 0.029 | E15: 0.029 | F15: ASSUMPTION
A16: U7 | B16: Stripe fee fixed $/txn | C16: 0.3 | D16: 0.3 | E16: 0.3 | F16: ASSUMPTION
A17: U8 | B17: Stripe basis 1=fee slice 0=full GMV | C17: 1 | D17: 1 | E17: 1 | F17: ASSUMPTION recommended fee-slice
A18: U9 | B18: Partner referral % of GMV blended | C18: 0.01 | D18: 0.008 | E18: 0.005 | F18: ASSUMPTION
A19: U10 | B19: SMS/email $/booking | C19: 1.25 | D19: 1 | E19: 0.75 | F19: ASSUMPTION
A20: U11 | B20: Weather drag % of platform revenue | C20: 0.06 | D20: 0.04 | E20: 0.025 | F20: ASSUMPTION
A21: V1 | B21: Y1 completed bookings | C21: 450 | D21: 900 | E21: 1200 | F21: ASSUMPTION
A22: V2 | B22: Y2 bookings | C22: 669 | D22: 1395 | E22: 1897 | F22: ASSUMPTION
A23: V3 | B23: Y3 bookings | C23: 995 | D23: 2163 | E23: 3000 | F23: ASSUMPTION
A24: V4 | B24: Y4 bookings | C24: 1480 | D24: 3354 | E24: 4743 | F24: ASSUMPTION
A25: V5 | B25: Y5 bookings | C25: 2200 | D25: 5200 | E25: 7500 | F25: ASSUMPTION
... A39: CH3 | B39: OTA commission if used later | C39: 0.25 | D39: 0.25 | E39: 0.22 | F39: SOURCED ~20-30%
A42: LEGEND
B43: Yellow = INPUT
B44: Green = CALCULATED
A46: Partner keeps ~(1−take)×GMV (not GCCN OpEx). Platform COGS = Stripe(fee-slice)+referral+SMS+paid CAC+fixed OpEx.
A47: Sources in BUSINESS_PLAN_5YR.md (GSOBT/ATD, FareHarbor ~6%, OTA ~20-30%).

Sheet Annual_PnL
A1: GCCN Annual P&L — Y1–Y5 × Three Scenarios (pre-tax)
A2: GMV=bookings×AOV(with lift). Revenue=GMV×effective take×(1−weather drag). Stripe on fee slice if U8=1.
A4: Metric | B4: Y1 Cons | C4: Y1 Base | D4: Y1 Upsi | E4: Y2 Cons | F4: Y2 Base | G4: Y2 Upsi | H4: Y3 Cons | I4: Y3 Base | J4: Y3 Upsi | K4: Y4 Cons | L4: Y4 Base | M4: Y4 Upsi | N4: Y5 Cons | O4: Y5 Base | P4: Y5 Upsi
A5: Bookings | B5: =Assumptions!C21 | C5: =Assumptions!D21 | D5: =Assumptions!E21 | E5: =Assumptions!C22 | F5: =Assumptions!D22 | G5: =Assumptions!E22 | H5: =Assumptions!C23 | I5: =Assumptions!D23 | J5: =Assumptions!E23 | K5: =Assumptions!C24 | L5: =Assumptions!D24 | M5: =Assumptions!E24 | N5: =Assumptions!C25 | O5: =Assumptions!D25 | P5: =Assumptions!E25
A6: AOV ($) | B6: =(Assumptions!C10*(1+Assumptions!C26)^(1-1)) | C6: =(Assumptions!D10*(1+Assumptions!D26)^(1-1)) | D6: =(Assumptions!E10*(1+Assumptions!E26)^(1-1)) | E6: =(Assumptions!C10*(1+Assumptions!C26)^(2-1)) | F6: =(Assumptions!D10*(1+Assumptions!D26)^(2-1)) | G6: =(Assumptions!E10*(1+Assumptions!E26)^(2-1)) | H6: =(Assumptions!C10*(1+Assumptions!C26)^(3-1)) | I6: =(Assumptions!D10*(1+Assumptions!D26)^(3-1)) | J6: =(Assumptions!E10*(1+Assumptions!E26)^(3-1)) | K6: =(Assumptions!C10*(1+Assumptions!C26)^(4-1)) | L6: =(Assumptions!D10*(1+Assumptions!D26)^(4-1)) | M6: =(Assumptions!E10*(1+Assumptions!E26)^(4-1)) | N6: =(Assumptions!C10*(1+Assumptions!C26)^(5-1)) | O6: =(Assumptions!D10*(1+Assumptions!D26)^(5-1)) | P6: =(Assumptions!E10*(1+Assumptions!E26)^(5-1))
A7: GMV ($) | B7: =(Assumptions!C21*(Assumptions!C10*(1+Assumptions!C26)^(1-1))) | C7: =(Assumptions!D21*(Assumptions!D10*(1+Assumptions!D26)^(1-1))) | D7: =(Assumptions!E21*(Assumptions!E10*(1+Assumptions!E26)^(1-1))) | E7: =(Assumptions!C22*(Assumptions!C10*(1+Assumptions!C26)^(2-1))) | F7: =(Assumptions!D22*(Assumptions!D10*(1+Assumptions!D26)^(2-1))) | G7: =(Assumptions!E22*(Assumptions!E10*(1+Assumptions!E26)^(2-1))) | H7: =(Assumptions!C23*(Assumptions!C10*(1+Assumptions!C26)^(3-1))) | I7: =(Assumptions!D23*(Assumptions!D10*(1+Assumptions!D26)^(3-1))) | J7: =(Assumptions!E23*(Assumptions!E10*(1+Assumptions!E26)^(3-1))) | K7: =(Assumptions!C24*(Assumptions!C10*(1+Assumptions!C26)^(4-1))) | L7: =(Assumptions!D24*(Assumptions!D10*(1+Assumptions!D26)^(4-1))) | M7: =(Assumptions!E24*(Assumptions!E10*(1+Assumptions!E26)^(4-1))) | N7: =(Assumptions!C25*(Assumptions!C10*(1+Assumptions!C26)^(5-1))) | O7: =(Assumptions!D25*(Assumptions!D10*(1+Assumptions!D26)^(5-1))) | P7: =(Assumptions!E25*(Assumptions!E10*(1+Assumptions!E26)^(5-1)))
A8: Effective take rate | B8: =(Assumptions!C11+Assumptions!C12) | C8: =(Assumptions!D11+Assumptions!D12) | D8: =(Assumptions!E11+Assumptions!E12) | E8: =(Assumptions!C11+Assumptions!C12) | F8: =(Assumptions!D11+Assumptions!D12) | G8: =(Assumptions!E11+Assumptions!E12) | H8: =(Assumptions!C11+Assumptions!C12) | I8: =(Assumptions!D11+Assumptions!D12) | J8: =(Assumptions!E11+Assumptions!E12) | K8: =(Assumptions!C11+Assumptions!C12) | L8: =(Assumptions!D11+Assumptions!D12) | M8: =(Assumptions!E11+Assumptions!E12) | N8: =(Assumptions!C11+Assumptions!C12) | O8: =(Assumptions!D11+Assumptions!D12) | P8: =(Assumptions!E11+Assumptions!E12)
A9: Gross platform revenue ($) | B9: =((Assumptions!C21*(Assumptions!C10*(1+Assumptions!C26)^(1-1)))*(Assumptions!C11+Assumptions!C12)) | C9: =((Assumptions!D21*(Assumptions!D10*(1+Assumptions!D26)^(1-1)))*(Assumptions!D11+Assumptions!D12)) | D9: =((Assumptions!E21*(Assumptions!E10*(1+Assumptions!E26)^(1-1)))*(Assumptions!E11+Assumptions!E12)) | E9: =((Assumptions!C22*(Assumptions!C10*(1+Assumptions!C26)^(2-1)))*(Assumptions!C11+Assumptions!C12)) | F9: =((Assumptions!D22*(Assumptions!D10*(1+Assumptions!D26)^(2-1)))*(Assumptions!D11+Assumptions!D12)) | G9: =((Assumptions!E22*(Assumptions!E10*(1+Assumptions!E26)^(2-1)))*(Assumptions!E11+Assumptions!E12)) | H9: =((Assumptions!C23*(Assumptions!C10*(1+Assumptions!C26)^(3-1)))*(Assumptions!C11+Assumptions!C12)) | I9: =((Assumptions!D23*(Assumptions!D10*(1+Assumptions!D26)^(3-1)))*(Assumptions!D11+Assumptions!D12)) | J9: =((Assumptions!E23*(Assumptions!E10*(1+Assumptions!E26)^(3-1)))*(Assumptions!E11+Assumptions!E12)) | K9: =((Assumptions!C24*(Assumptions!C10*(1+Assumptions!C26)^(4-1)))*(Assumptions!C11+Assumptions!C12)) | L9: =((Assumptions!D24*(Assumptions!D10*(1+Assumptions!D26)^(4-1)))*(Assumptions!D11+Assumptions!D12)) | M9: =((Assumptions!E24*(Assumptions!E10*(1+Assumptions!E26)^(4-1)))*(Assumptions!E11+Assumptions!E12)) | N9: =((Assumptions!C25*(Assumptions!C10*(1+Assumptions!C26)^(5-1)))*(Assumptions!C11+Assumptions!C12)) | O9: =((Assumptions!D25*(Assumptions!D10*(1+Assumptions!D26)^(5-1)))*(Assumptions!D11+Assumptions!D12)) | P9: =((Assumptions!E25*(Assumptions!E10*(1+Assumptions!E26)^(5-1)))*(Assumptions!E11+Assumptions!E12))
A10: Revenue after weather drag ($) | B10: =(((Assumptions!C21*(Assumptions!C10*(1+Assumptions!C26)^(1-1)))*(Assumptions!C11+Assumptions!C12))*(1-Assumptions!C20)) | C10: =(((Assumptions!D21*(Assumptions!D10*(1+Assumptions!D26)^(1-1)))*(Assumptions!D11+Assumptions!D12))*(1-Assumptions!D20)) | D10: =(((Assumptions!E21*(Assumptions!E10*(1+Assumptions!E26)^(1-1)))*(Assumptions!E11+Assumptions!E12))*(1-Assumptions!E20)) | E10: =(((Assumptions!C22*(Assumptions!C10*(1+Assumptions!C26)^(2-1)))*(Assumptions!C11+Assumptions!C12))*(1-Assumptions!C20)) | F10: =(((Assumptions!D22*(Assumptions!D10*(1+Assumptions!D26)^(2-1)))*(Assumptions!D11+Assumptions!D12))*(1-Assumptions!D20)) | G10: =(((Assumptions!E22*(Assumptions!E10*(1+Assumptions!E26)^(2-1)))*(Assumptions!E11+Assumptions!E12))*(1-Assumptions!E20)) | H10: =(((Assumptions!C23*(Assumptions!C10*(1+Assumptions!C26)^(3-1)))*(Assumptions!C11+Assumptions!C12))*(1-Assumptions!C20)) | I10: =(((Assumptions!D23*(Assumptions!D10*(1+Assumptions!D26)^(3-1)))*(Assumptions!D11+Assumptions!D12))*(1-Assumptions!D20)) | J10: =(((Assumptions!E23*(Assumptions!E10*(1+Assumptions!E26)^(3-1)))*(Assumptions!E11+Assumptions!E12))*(1-Assumptions!E20)) | K10: =(((Assumptions!C24*(Assumptions!C10*(1+Assumptions!C26)^(4-1)))*(Assumptions!C11+Assumptions!C12))*(1-Assumptions!C20)) | L10: =(((Assumptions!D24*(Assumptions!D10*(1+Assumptions!D26)^(4-1)))*(Assumptions!D11+Assumptions!D12))*(1-Assumptions!D20)) | M10: =(((Assumptions!E24*(Assumptions!E10*(1+Assumptions!E26)^(4-1)))*(Assumptions!E11+Assumptions!E12))*(1-Assumptions!E20)) | N10: =(((Assumptions!C25*(Assumptions!C10*(1+Assumptions!C26)^(5-1)))*(Assumptions!C11+Assumptions!C12))*(1-Assumptions!C20)) | O10: =(((Assumptions!D25*(Assumptions!D10*(1+Assumptions!D26)^(5-1)))*(Assumptions!D11+Assumptions!D12))*(1-Assumptions!D20)) | P10: =(((Assumptions!E25*(Assumptions!E10*(1+Assumptions!E26)^(5-1)))*(Assumptions!E11+Assumptions!E12))*(1-Assumptions!E20))
A11: Stripe fees ($) | B11: =(IF(Assumptions!C17=1,(((Assumptions!C21*(Assumptions!C10*(1+Assumptions!C26)^(1-1)))*(Assumptions!C11+Assumptions!C12))*(1-Assumptions!C20))*Assumptions!C15+Assumptions!C21*Assumptions!C16,(Assumptions!C21*(Assumptions!C10*(1+Assumptions!C26)^(1-1)))*Assumptions!C15+Assumptions!C21*Assumptions!C16)) | C11: =(IF(Assumptions!D17=1,(((Assumptions!D21*(Assumptions!D10*(1+Assumptions!D26)^(1-1)))*(Assumptions!D11+Assumptions!D12))*(1-Assumptions!D20))*Assumptions!D15+Assumptions!D21*Assumptions!D16,(Assumptions!D21*(Assumptions!D10*(1+Assumptions!D26)^(1-1)))*Assumptions!D15+Assumptions!D21*Assumptions!D16)) | D11: =(IF(Assumptions!E17=1,(((Assumptions!E21*(Assumptions!E10*(1+Assumptions!E26)^(1-1)))*(Assumptions!E11+Assumptions!E12))*(1-Assumptions!E20))*Assumptions!E15+Assumptions!E21*Assumptions!E16,(Assumptions!E21*(Assumptions!E10*(1+Assumptions!E26)^(1-1)))*Assumptions!E15+Assumptions!E21*Assumptions!E16)) | E11: =(IF(Assumptions!C17=1,(((Assumptions!C22*(Assumptions!C10*(1+Assumptions!C26)^(2-1)))*(Assumptions!C11+Assumptions!C12))*(1-Assumptions!C20))*Assumptions!C15+Assumptions!C22*Assumptions!C16,(Assumptions!C22*(Assumptions!C10*(1+Assumptions!C26)^(2-1)))*Assumptions!C15+Assumptions!C22*Assumptions!C16)) | F11: =(IF(Assumptions!D17=1,(((Assumptions!D22*(Assumptions!D10*(1+Assumptions!D26)^(2-1)))*(Assumptions!D11+Assumptions!D12))*(1-Assumptions!D20))*Assumptions!D15+Assumptions!D22*Assumptions!D16,(Assumptions!D22*(Assumptions!D10*(1+Assumptions!D26)^(2-1)))*Assumptions!D15+Assumptions!D22*Assumptions!D16)) | G11: =(IF(Assumptions!E17=1,(((Assumptions!E22*(Assumptions!E10*(1+Assumptions!E26)^(2-1)))*(Assumptions!E11+Assumptions!E12))*(1-Assumptions!E20))*Assumptions!E15+Assumptions!E22*Assumptions!E16,(Assumptions!E22*(Assumptions!E10*(1+Assumptions!E26)^(2-1)))*Assumptions!E15+Assumptions!E22*Assumptions!E16)) | H11: =(IF(Assumptions!C17=1,(((Assumptions!C23*(Assumptions!C10*(1+Assumptions!C26)^(3-1)))*(Assumptions!C11+Assumptions!C12))*(1-Assumptions!C20))*Assumptions!C15+Assumptions!C23*Assumptions!C16,(Assumptions!C23*(Assumptions!C10*(1+Assumptions!C26)^(3-1)))*Assumptions!C15+Assumptions!C23*Assumptions!C16)) | I11: =(IF(Assumptions!D17=1,(((Assumptions!D23*(Assumptions!D10*(1+Assumptions!D26)^(3-1)))*(Assumptions!D11+Assumptions!D12))*(1-Assumptions!D20))*Assumptions!D15+Assumptions!D23*Assumptions!D16,(Assumptions!D23*(Assumptions!D10*(1+Assumptions!D26)^(3-1)))*Assumptions!D15+Assumptions!D23*Assumptions!D16)) | J11: =(IF(Assumptions!E17=1,(((Assumptions!E23*(Assumptions!E10*(1+Assumptions!E26)^(3-1)))*(Assumptions!E11+Assumptions!E12))*(1-Assumptions!E20))*Assumptions!E15+Assumptions!E23*Assumptions!E16,(Assumptions!E23*(Assumptions!E10*(1+Assumptions!E26)^(3-1)))*Assumptions!E15+Assumptions!E23*Assumptions!E16)) | K11: =(IF(Assumptions!C17=1,(((Assumptions!C24*(Assumptions!C10*(1+Assumptions!C26)^(4-1)))*(Assumptions!C11+Assumptions!C12))*(1-Assumptions!C20))*Assumptions!C15+Assumptions!C24*Assumptions!C16,(Assumptions!C24*(Assumptions!C10*(1+Assumptions!C26)^(4-1)))*Assumptions!C15+Assumptions!C24*Assumptions!C16)) | L11: =(IF(Assumptions!D17=1,(((Assumptions!D24*(Assumptions!D10*(1+Assumptions!D26)^(4-1)))*(Assumptions!D11+Assumptions!D12))*(1-Assumptions!D20))*Assumptions!D15+Assumptions!D24*Assumptions!D16,(Assumptions!D24*(Assumptions!D10*(1+Assumptions!D26)^(4-1)))*Assumptions!D15+Assumptions!D24*Assumptions!D16)) | M11: =(IF(Assumptions!E17=1,(((Assumptions!E24*(Assumptions!E10*(1+Assumptions!E26)^(4-1)))*(Assumptions!E11+Assumptions!E12))*(1-Assumptions!E20))*Assumptions!E15+Assumptions!E24*Assumptions!E16,(Assumptions!E24*(Assumptions!E10*(1+Assumptions!E26)^(4-1)))*Assumptions!E15+Assumptions!E24*Assumptions!E16)) | N11: =(IF(Assumptions!C17=1,(((Assumptions!C25*(Assumptions!C10*(1+Assumptions!C26)^(5-1)))*(Assumptions!C11+Assumptions!C12))*(1-Assumptions!C20))*Assumptions!C15+Assumptions!C25*Assumptions!C16,(Assumptions!C25*(Assumptions!C10*(1+Assumptions!C26)^(5-1)))*Assumptions!C15+Assumptions!C25*Assumptions!C16)) | O11: =(IF(Assumptions!D17=1,(((Assumptions!D25*(Assumptions!D10*(1+Assumptions!D26)^(5-1)))*(Assumptions!D11+Assumptions!D12))*(1-Assumptions!D20))*Assumptions!D15+Assumptions!D25*Assumptions!D16,(Assumptions!D25*(Assumptions!D10*(1+Assumptions!D26)^(5-1)))*Assumptions!D15+Assumptions!D25*Assumptions!D16)) | P11: =(IF(Assumptions!E17=1,(((Assumptions!E25*(Assumptions!E10*(1+Assumptions!E26)^(5-1)))*(Assumptions!E11+Assumptions!E12))*(1-Assumptions!E20))*Assumptions!E15+Assumptions!E25*Assumptions!E16,(Assumptions!E25*(Assumptions!E10*(1+Assumptions!E26)^(5-1)))*Assumptions!E15+Assumptions!E25*Assumptions!E16))
A12: Partner referral credits ($) | B12: =((Assumptions!C21*(Assumptions!C10*(1+Assumptions!C26)^(1-1)))*Assumptions!C18) | C12: =((Assumptions!D21*(Assumptions!D10*(1+Assumptions!D26)^(1-1)))*Assumptions!D18) | D12: =((Assumptions!E21*(Assumptions!E10*(1+Assumptions!E26)^(1-1)))*Assumptions!E18) | E12: =((Assumptions!C22*(Assumptions!C10*(1+Assumptions!C26)^(2-1)))*Assumptions!C18) | F12: =((Assumptions!D22*(Assumptions!D10*(1+Assumptions!D26)^(2-1)))*Assumptions!D18) | G12: =((Assumptions!E22*(Assumptions!E10*(1+Assumptions!E26)^(2-1)))*Assumptions!E18) | H12: =((Assumptions!C23*(Assumptions!C10*(1+Assumptions!C26)^(3-1)))*Assumptions!C18) | I12: =((Assumptions!D23*(Assumptions!D10*(1+Assumptions!D26)^(3-1)))*Assumptions!D18) | J12: =((Assumptions!E23*(Assumptions!E10*(1+Assumptions!E26)^(3-1)))*Assumptions!E18) | K12: =((Assumptions!C24*(Assumptions!C10*(1+Assumptions!C26)^(4-1)))*Assumptions!C18) | L12: =((Assumptions!D24*(Assumptions!D10*(1+Assumptions!D26)^(4-1)))*Assumptions!D18) | M12: =((Assumptions!E24*(Assumptions!E10*(1+Assumptions!E26)^(4-1)))*Assumptions!E18) | N12: =((Assumptions!C25*(Assumptions!C10*(1+Assumptions!C26)^(5-1)))*Assumptions!C18) | O12: =((Assumptions!D25*(Assumptions!D10*(1+Assumptions!D26)^(5-1)))*Assumptions!D18) | P12: =((Assumptions!E25*(Assumptions!E10*(1+Assumptions!E26)^(5-1)))*Assumptions!E18)
A13: SMS/email variable ($) | B13: =(Assumptions!C21*Assumptions!C19) | C13: =(Assumptions!D21*Assumptions!D19) | D13: =(Assumptions!E21*Assumptions!E19) | E13: =(Assumptions!C22*Assumptions!C19) | F13: =(Assumptions!D22*Assumptions!D19) | G13: =(Assumptions!E22*Assumptions!E19) | H13: =(Assumptions!C23*Assumptions!C19) | I13: =(Assumptions!D23*Assumptions!D19) | J13: =(Assumptions!E23*Assumptions!E19) | K13: =(Assumptions!C24*Assumptions!C19) | L13: =(Assumptions!D24*Assumptions!D19) | M13: =(Assumptions!E24*Assumptions!E19) | N13: =(Assumptions!C25*Assumptions!C19) | O13: =(Assumptions!D25*Assumptions!D19) | P13: =(Assumptions!E25*Assumptions!E19)
A14: Variable COGS subtotal ($) | B14: =((IF(Assumptions!C17=1,(((Assumptions!C21*(Assumptions!C10*(1+Assumptions!C26)^(1-1)))*(Assumptions!C11+Assumptions!C12))*(1-Assumptions!C20))*Assumptions!C15+Assumptions!C21*Assumptions!C16,(Assumptions!C21*(Assumptions!C10*(1+Assumptions!C26)^(1-1)))*Assumptions!C15+Assumptions!C21*Assumptions!C16))+((Assumptions!C21*(Assumptions!C10*(1+Assumptions!C26)^(1-1)))*Assumptions!C18)+(Assumptions!C21*Assumptions!C19)) | C14: =((IF(Assumptions!D17=1,(((Assumptions!D21*(Assumptions!D10*(1+Assumptions!D26)^(1-1)))*(Assumptions!D11+Assumptions!D12))*(1-Assumptions!D20))*Assumptions!D15+Assumptions!D21*Assumptions!D16,(Assumptions!D21*(Assumptions!D10*(1+Assumptions!D26)^(1-1)))*Assumptions!D15+Assumptions!D21*Assumptions!D16))+((Assumptions!D21*(Assumptions!D10*(1+Assumptions!D26)^(1-1)))*Assumptions!D18)+(Assumptions!D21*Assumptions!D19)) | D14: =((IF(Assumptions!E17=1,(((Assumptions!E21*(Assumptions!E10*(1+Assumptions!E26)^(1-1)))*(Assumptions!E11+Assumptions!E12))*(1-Assumptions!E20))*Assumptions!E15+Assumptions!E21*Assumptions!E16,(Assumptions!E21*(Assumptions!E10*(1+Assumptions!E26)^(1-1)))*Assumptions!E15+Assumptions!E21*Assumptions!E16))+((Assumptions!E21*(Assumptions!E10*(1+Assumptions!E26)^(1-1)))*Assumptions!E18)+(Assumptions!E21*Assumptions!E19)) | E14: =((IF(Assumptions!C17=1,(((Assumptions!C22*(Assumptions!C10*(1+Assumptions!C26)^(2-1)))*(Assumptions!C11+Assumptions!C12))*(1-Assumptions!C20))*Assumptions!C15+Assumptions!C22*Assumptions!C16,(Assumptions!C22*(Assumptions!C10*(1+Assumptions!C26)^(2-1)))*Assumptions!C15+Assumptions!C22*Assumptions!C16))+((Assumptions!C22*(Assumptions!C10*(1+Assumptions!C26)^(2-1)))*Assumptions!C18)+(Assumptions!C22*Assumptions!C19)) | F14: =((IF(Assumptions!D17=1,(((Assumptions!D22*(Assumptions!D10*(1+Assumptions!D26)^(2-1)))*(Assumptions!D11+Assumptions!D12))*(1-Assumptions!D20))*Assumptions!D15+Assumptions!D22*Assumptions!D16,(Assumptions!D22*(Assumptions!D10*(1+Assumptions!D26)^(2-1)))*Assumptions!D15+Assumptions!D22*Assumptions!D16))+((Assumptions!D22*(Assumptions!D10*(1+Assumptions!D26)^(2-1)))*Assumptions!D18)+(Assumptions!D22*Assumptions!D19)) | G14: =((IF(Assumptions!E17=1,(((Assumptions!E22*(Assumptions!E10*(1+Assumptions!E26)^(2-1)))*(Assumptions!E11+Assumptions!E12))*(1-Assumptions!E20))*Assumptions!E15+Assumptions!E22*Assumptions!E16,(Assumptions!E22*(Assumptions!E10*(1+Assumptions!E26)^(2-1)))*Assumptions!E15+Assumptions!E22*Assumptions!E16))+((Assumptions!E22*(Assumptions!E10*(1+Assumptions!E26)^(2-1)))*Assumptions!E18)+(Assumptions!E22*Assumptions!E19)) | H14: =((IF(Assumptions!C17=1,(((Assumptions!C23*(Assumptions!C10*(1+Assumptions!C26)^(3-1)))*(Assumptions!C11+Assumptions!C12))*(1-Assumptions!C20))*Assumptions!C15+Assumptions!C23*Assumptions!C16,(Assumptions!C23*(Assumptions!C10*(1+Assumptions!C26)^(3-1)))*Assumptions!C15+Assumptions!C23*Assumptions!C16))+((Assumptions!C23*(Assumptions!C10*(1+Assumptions!C26)^(3-1)))*Assumptions!C18)+(Assumptions!C23*Assumptions!C19)) | I14: =((IF(Assumptions!D17=1,(((Assumptions!D23*(Assumptions!D10*(1+Assumptions!D26)^(3-1)))*(Assumptions!D11+Assumptions!D12))*(1-Assumptions!D20))*Assumptions!D15+Assumptions!D23*Assumptions!D16,(Assumptions!D23*(Assumptions!D10*(1+Assumptions!D26)^(3-1)))*Assumptions!D15+Assumptions!D23*Assumptions!D16))+((Assumptions!D23*(Assumptions!D10*(1+Assumptions!D26)^(3-1)))*Assumptions!D18)+(Assumptions!D23*Assumptions!D19)) | J14: =((IF(Assumptions!E17=1,(((Assumptions!E23*(Assumptions!E10*(1+Assumptions!E26)^(3-1)))*(Assumptions!E11+Assumptions!E12))*(1-Assumptions!E20))*Assumptions!E15+Assumptions!E23*Assumptions!E16,(Assumptions!E23*(Assumptions!E10*(1+Assumptions!E26)^(3-1)))*Assumptions!E15+Assumptions!E23*Assumptions!E16))+((Assumptions!E23*(Assumptions!E10*(1+Assumptions!E26)^(3-1)))*Assumptions!E18)+(Assumptions!E23*Assumptions!E19)) | K14: =((IF(Assumptions!C17=1,(((Assumptions!C24*(Assumptions!C10*(1+Assumptions!C26)^(4-1)))*(Assumptions!C11+Assumptions!C12))*(1-Assumptions!C20))*Assumptions!C15+Assumptions!C24*Assumptions!C16,(Assumptions!C24*(Assumptions!C10*(1+Assumptions!C26)^(4-1)))*Assumptions!C15+Assumptions!C24*Assumptions!C16))+((Assumptions!C24*(Assumptions!C10*(1+Assumptions!C26)^(4-1)))*Assumptions!C18)+(Assumptions!C24*Assumptions!C19)) | L14: =((IF(Assumptions!D17=1,(((Assumptions!D24*(Assumptions!D10*(1+Assumptions!D26)^(4-1)))*(Assumptions!D11+Assumptions!D12))*(1-Assumptions!D20))*Assumptions!D15+Assumptions!D24*Assumptions!D16,(Assumptions!D24*(Assumptions!D10*(1+Assumptions!D26)^(4-1)))*Assumptions!D15+Assumptions!D24*Assumptions!D16))+((Assumptions!D24*(Assumptions!D10*(1+Assumptions!D26)^(4-1)))*Assumptions!D18)+(Assumptions!D24*Assumptions!D19)) | M14: =((IF(Assumptions!E17=1,(((Assumptions!E24*(Assumptions!E10*(1+Assumptions!E26)^(4-1)))*(Assumptions!E11+Assumptions!E12))*(1-Assumptions!E20))*Assumptions!E15+Assumptions!E24*Assumptions!E16,(Assumptions!E24*(Assumptions!E10*(1+Assumptions!E26)^(4-1)))*Assumptions!E15+Assumptions!E24*Assumptions!E16))+((Assumptions!E24*(Assumptions!E10*(1+Assumptions!E26)^(4-1)))*Assumptions!E18)+(Assumptions!E24*Assumptions!E19)) | N14: =((IF(Assumptions!C17=1,(((Assumptions!C25*(Assumptions!C10*(1+Assumptions!C26)^(5-1)))*(Assumptions!C11+Assumptions!C12))*(1-Assumptions!C20))*Assumptions!C15+Assumptions!C25*Assumptions!C16,(Assumptions!C25*(Assumptions!C10*(1+Assumptions!C26)^(5-1)))*Assumptions!C15+Assumptions!C25*Assumptions!C16))+((Assumptions!C25*(Assumptions!C10*(1+Assumptions!C26)^(5-1)))*Assumptions!C18)+(Assumptions!C25*Assumptions!C19)) | O14: =((IF(Assumptions!D17=1,(((Assumptions!D25*(Assumptions!D10*(1+Assumptions!D26)^(5-1)))*(Assumptions!D11+Assumptions!D12))*(1-Assumptions!D20))*Assumptions!D15+Assumptions!D25*Assumptions!D16,(Assumptions!D25*(Assumptions!D10*(1+Assumptions!D26)^(5-1)))*Assumptions!D15+Assumptions!D25*Assumptions!D16))+((Assumptions!D25*(Assumptions!D10*(1+Assumptions!D26)^(5-1)))*Assumptions!D18)+(Assumptions!D25*Assumptions!D19)) | P14: =((IF(Assumptions!E17=1,(((Assumptions!E25*(Assumptions!E10*(1+Assumptions!E26)^(5-1)))*(Assumptions!E11+Assumptions!E12))*(1-Assumptions!E20))*Assumptions!E15+Assumptions!E25*Assumptions!E16,(Assumptions!E25*(Assumptions!E10*(1+Assumptions!E26)^(5-1)))*Assumptions!E15+Assumptions!E25*Assumptions!E16))+((Assumptions!E25*(Assumptions!E10*(1+Assumptions!E26)^(5-1)))*Assumptions!E18)+(Assumptions!E25*Assumptions!E19))
A15: Contribution after var COGS ($) | B15: =((((Assumptions!C21*(Assumptions!C10*(1+Assumptions!C26)^(1-1)))*(Assumptions!C11+Assumptions!C12))*(1-Assumptions!C20))-((IF(Assumptions!C17=1,(((Assumptions!C21*(Assumptions!C10*(1+Assumptions!C26)^(1-1)))*(Assumptions!C11+Assumptions!C12))*(1-Assumptions!C20))*Assumptions!C15+Assumptions!C21*Assumptions!C16,(Assumptions!C21*(Assumptions!C10*(1+Assumptions!C26)^(1-1)))*Assumptions!C15+Assumptions!C21*Assumptions!C16))+((Assumptions!C21*(Assumptions!C10*(1+Assumptions!C26)^(1-1)))*Assumptions!C18)+(Assumptions!C21*Assumptions!C19))) | C15: =((((Assumptions!D21*(Assumptions!D10*(1+Assumptions!D26)^(1-1)))*(Assumptions!D11+Assumptions!D12))*(1-Assumptions!D20))-((IF(Assumptions!D17=1,(((Assumptions!D21*(Assumptions!D10*(1+Assumptions!D26)^(1-1)))*(Assumptions!D11+Assumptions!D12))*(1-Assumptions!D20))*Assumptions!D15+Assumptions!D21*Assumptions!D16,(Assumptions!D21*(Assumptions!D10*(1+Assumptions!D26)^(1-1)))*Assumptions!D15+Assumptions!D21*Assumptions!D16))+((Assumptions!D21*(Assumptions!D10*(1+Assumptions!D26)^(1-1)))*Assumptions!D18)+(Assumptions!D21*Assumptions!D19))) | D15: =((((Assumptions!E21*(Assumptions!E10*(1+Assumptions!E26)^(1-1)))*(Assumptions!E11+Assumptions!E12))*(1-Assumptions!E20))-((IF(Assumptions!E17=1,(((Assumptions!E21*(Assumptions!E10*(1+Assumptions!E26)^(1-1)))*(Assumptions!E11+Assumptions!E12))*(1-Assumptions!E20))*Assumptions!E15+Assumptions!E21*Assumptions!E16,(Assumptions!E21*(Assumptions!E10*(1+Assumptions!E26)^(1-1)))*Assumptions!E15+Assumptions!E21*Assumptions!E16))+((Assumptions!E21*(Assumptions!E10*(1+Assumptions!E26)^(1-1)))*Assumptions!E18)+(Assumptions!E21*Assumptions!E19))) | E15: =((((Assumptions!C22*(Assumptions!C10*(1+Assumptions!C26)^(2-1)))*(Assumptions!C11+Assumptions!C12))*(1-Assumptions!C20))-((IF(Assumptions!C17=1,(((Assumptions!C22*(Assumptions!C10*(1+Assumptions!C26)^(2-1)))*(Assumptions!C11+Assumptions!C12))*(1-Assumptions!C20))*Assumptions!C15+Assumptions!C22*Assumptions!C16,(Assumptions!C22*(Assumptions!C10*(1+Assumptions!C26)^(2-1)))*Assumptions!C15+Assumptions!C22*Assumptions!C16))+((Assumptions!C22*(Assumptions!C10*(1+Assumptions!C26)^(2-1)))*Assumptions!C18)+(Assumptions!C22*Assumptions!C19))) | F15: =((((Assumptions!D22*(Assumptions!D10*(1+Assumptions!D26)^(2-1)))*(Assumptions!D11+Assumptions!D12))*(1-Assumptions!D20))-((IF(Assumptions!D17=1,(((Assumptions!D22*(Assumptions!D10*(1+Assumptions!D26)^(2-1)))*(Assumptions!D11+Assumptions!D12))*(1-Assumptions!D20))*Assumptions!D15+Assumptions!D22*Assumptions!D16,(Assumptions!D22*(Assumptions!D10*(1+Assumptions!D26)^(2-1)))*Assumptions!D15+Assumptions!D22*Assumptions!D16))+((Assumptions!D22*(Assumptions!D10*(1+Assumptions!D26)^(2-1)))*Assumptions!D18)+(Assumptions!D22*Assumptions!D19))) | G15: =((((Assumptions!E22*(Assumptions!E10*(1+Assumptions!E26)^(2-1)))*(Assumptions!E11+Assumptions!E12))*(1-Assumptions!E20))-((IF(Assumptions!E17=1,(((Assumptions!E22*(Assumptions!E10*(1+Assumptions!E26)^(2-1)))*(Assumptions!E11+Assumptions!E12))*(1-Assumptions!E20))*Assumptions!E15+Assumptions!E22*Assumptions!E16,(Assumptions!E22*(Assumptions!E10*(1+Assumptions!E26)^(2-1)))*Assumptions!E15+Assumptions!E22*Assumptions!E16))+((Assumptions!E22*(Assumptions!E10*(1+Assumptions!E26)^(2-1)))*Assumptions!E18)+(Assumptions!E22*Assumptions!E19))) | H15: =((((Assumptions!C23*(Assumptions!C10*(1+Assumptions!C26)^(3-1)))*(Assumptions!C11+Assumptions!C12))*(1-Assumptions!C20))-((IF(Assumptions!C17=1,(((Assumptions!C23*(Assumptions!C10*(1+Assumptions!C26)^(3-1)))*(Assumptions!C11+Assumptions!C12))*(1-Assumptions!C20))*Assumptions!C15+Assumptions!C23*Assumptions!C16,(Assumptions!C23*(Assumptions!C10*(1+Assumptions!C26)^(3-1)))*Assumptions!C15+Assumptions!C23*Assumptions!C16))+((Assumptions!C23*(Assumptions!C10*(1+Assumptions!C26)^(3-1)))*Assumptions!C18)+(Assumptions!C23*Assumptions!C19))) | I15: =((((Assumptions!D23*(Assumptions!D10*(1+Assumptions!D26)^(3-1)))*(Assumptions!D11+Assumptions!D12))*(1-Assumptions!D20))-((IF(Assumptions!D17=1,(((Assumptions!D23*(Assumptions!D10*(1+Assumptions!D26)^(3-1)))*(Assumptions!D11+Assumptions!D12))*(1-Assumptions!D20))*Assumptions!D15+Assumptions!D23*Assumptions!D16,(Assumptions!D23*(Assumptions!D10*(1+Assumptions!D26)^(3-1)))*Assumptions!D15+Assumptions!D23*Assumptions!D16))+((Assumptions!D23*(Assumptions!D10*(1+Assumptions!D26)^(3-1)))*Assumptions!D18)+(Assumptions!D23*Assumptions!D19))) | J15: =((((Assumptions!E23*(Assumptions!E10*(1+Assumptions!E26)^(3-1)))*(Assumptions!E11+Assumptions!E12))*(1-Assumptions!E20))-((IF(Assumptions!E17=1,(((Assumptions!E23*(Assumptions!E10*(1+Assumptions!E26)^(3-1)))*(Assumptions!E11+Assumptions!E12))*(1-Assumptions!E20))*Assumptions!E15+Assumptions!E23*Assumptions!E16,(Assumptions!E23*(Assumptions!E10*(1+Assumptions!E26)^(3-1)))*Assumptions!E15+Assumptions!E23*Assumptions!E16))+((Assumptions!E23*(Assumptions!E10*(1+Assumptions!E26)^(3-1)))*Assumptions!E18)+(Assumptions!E23*Assumptions!E19))) | K15: =((((Assumptions!C24*(Assumptions!C10*(1+Assumptions!C26)^(4-1)))*(Assumptions!C11+Assumptions!C12))*(1-Assumptions!C20))-((IF(Assumptions!C17=1,(((Assumptions!C24*(Assumptions!C10*(1+Assumptions!C26)^(4-1)))*(Assumptions!C11+Assumptions!C12))*(1-Assumptions!C20))*Assumptions!C15+Assumptions!C24*Assumptions!C16,(Assumptions!C24*(Assumptions!C10*(1+Assumptions!C26)^(4-1)))*Assumptions!C15+Assumptions!C24*Assumptions!C16))+((Assumptions!C24*(Assumptions!C10*(1+Assumptions!C26)^(4-1)))*Assumptions!C18)+(Assumptions!C24*Assumptions!C19))) | L15: =((((Assumptions!D24*(Assumptions!D10*(1+Assumptions!D26)^(4-1)))*(Assumptions!D11+Assumptions!D12))*(1-Assumptions!D20))-((IF(Assumptions!D17=1,(((Assumptions!D24*(Assumptions!D10*(1+Assumptions!D26)^(4-1)))*(Assumptions!D11+Assumptions!D12))*(1-Assumptions!D20))*Assumptions!D15+Assumptions!D24*Assumptions!D16,(Assumptions!D24*(Assumptions!D10*(1+Assumptions!D26)^(4-1)))*Assumptions!D15+Assumptions!D24*Assumptions!D16))+((Assumptions!D24*(Assumptions!D10*(1+Assumptions!D26)^(4-1)))*Assumptions!D18)+(Assumptions!D24*Assumptions!D19))) | M15: =((((Assumptions!E24*(Assumptions!E10*(1+Assumptions!E26)^(4-1)))*(Assumptions!E11+Assumptions!E12))*(1-Assumptions!E20))-((IF(Assumptions!E17=1,(((Assumptions!E24*(Assumptions!E10*(1+Assumptions!E26)^(4-1)))*(Assumptions!E11+Assumptions!E12))*(1-Assumptions!E20))*Assumptions!E15+Assumptions!E24*Assumptions!E16,(Assumptions!E24*(Assumptions!E10*(1+Assumptions!E26)^(4-1)))*Assumptions!E15+Assumptions!E24*Assumptions!E16))+((Assumptions!E24*(Assumptions!E10*(1+Assumptions!E26)^(4-1)))*Assumptions!E18)+(Assumptions!E24*Assumptions!E19))) | N15: =((((Assumptions!C25*(Assumptions!C10*(1+Assumptions!C26)^(5-1)))*(Assumptions!C11+Assumptions!C12))*(1-Assumptions!C20))-((IF(Assumptions!C17=1,(((Assumptions!C25*(Assumptions!C10*(1+Assumptions!C26)^(5-1)))*(Assumptions!C11+Assumptions!C12))*(1-Assumptions!C20))*Assumptions!C15+Assumptions!C25*Assumptions!C16,(Assumptions!C25*(Assumptions!C10*(1+Assumptions!C26)^(5-1)))*Assumptions!C15+Assumptions!C25*Assumptions!C16))+((Assumptions!C25*(Assumptions!C10*(1+Assumptions!C26)^(5-1)))*Assumptions!C18)+(Assumptions!C25*Assumptions!C19))) | O15: =((((Assumptions!D25*(Assumptions!D10*(1+Assumptions!D26)^(5-1)))*(Assumptions!D11+Assumptions!D12))*(1-Assumptions!D20))-((IF(Assumptions!D17=1,(((Assumptions!D25*(Assumptions!D10*(1+Assumptions!D26)^(5-1)))*(Assumptions!D11+Assumptions!D12))*(1-Assumptions!D20))*Assumptions!D15+Assumptions!D25*Assumptions!D16,(Assumptions!D25*(Assumptions!D10*(1+Assumptions!D26)^(5-1)))*Assumptions!D15+Assumptions!D25*Assumptions!D16))+((Assumptions!D25*(Assumptions!D10*(1+Assumptions!D26)^(5-1)))*Assumptions!D18)+(Assumptions!D25*Assumptions!D19))) | P15: =((((Assumptions!E25*(Assumptions!E10*(1+Assumptions!E26)^(5-1)))*(Assumptions!E11+Assumptions!E12))*(1-Assumptions!E20))-((IF(Assumptions!E17=1,(((Assumptions!E25*(Assumptions!E10*(1+Assumptions!E26)^(5-1)))*(Assumptions!E11+Assumptions!E12))*(1-Assumptions!E20))*Assumptions!E15+Assumptions!E25*Assumptions!E16,(Assumptions!E25*(Assumptions!E10*(1+Assumptions!E26)^(5-1)))*Assumptions!E15+Assumptions!E25*Assumptions!E16))+((Assumptions!E25*(Assumptions!E10*(1+Assumptions!E26)^(5-1)))*Assumptions!E18)+(Assumptions!E25*Assumptions!E19)))
A16: Paid acquisition spend ($) | B16: =(Assumptions!C21*(Assumptions!C28+(Assumptions!C29-Assumptions!C28)*(1-1)/4)*Assumptions!C27) | C16: =(Assumptions!D21*(Assumptions!D28+(Assumptions!D29-Assumptions!D28)*(1-1)/4)*Assumptions!D27) | D16: =(Assumptions!E21*(Assumptions!E28+(Assumptions!E29-Assumptions!E28)*(1-1)/4)*Assumptions!E27) | E16: =(Assumptions!C22*(Assumptions!C28+(Assumptions!C29-Assumptions!C28)*(2-1)/4)*Assumptions!C27) | F16: =(Assumptions!D22*(Assumptions!D28+(Assumptions!D29-Assumptions!D28)*(2-1)/4)*Assumptions!D27) | G16: =(Assumptions!E22*(Assumptions!E28+(Assumptions!E29-Assumptions!E28)*(2-1)/4)*Assumptions!E27) | H16: =(Assumptions!C23*(Assumptions!C28+(Assumptions!C29-Assumptions!C28)*(3-1)/4)*Assumptions!C27) | I16: =(Assumptions!D23*(Assumptions!D28+(Assumptions!D29-Assumptions!D28)*(3-1)/4)*Assumptions!D27) | J16: =(Assumptions!E23*(Assumptions!E28+(Assumptions!E29-Assumptions!E28)*(3-1)/4)*Assumptions!E27) | K16: =(Assumptions!C24*(Assumptions!C28+(Assumptions!C29-Assumptions!C28)*(4-1)/4)*Assumptions!C27) | L16: =(Assumptions!D24*(Assumptions!D28+(Assumptions!D29-Assumptions!D28)*(4-1)/4)*Assumptions!D27) | M16: =(Assumptions!E24*(Assumptions!E28+(Assumptions!E29-Assumptions!E28)*(4-1)/4)*Assumptions!E27) | N16: =(Assumptions!C25*(Assumptions!C28+(Assumptions!C29-Assumptions!C28)*(5-1)/4)*Assumptions!C27) | O16: =(Assumptions!D25*(Assumptions!D28+(Assumptions!D29-Assumptions!D28)*(5-1)/4)*Assumptions!D27) | P16: =(Assumptions!E25*(Assumptions!E28+(Assumptions!E29-Assumptions!E28)*(5-1)/4)*Assumptions!E27)
A17: Fixed + brand OpEx ($) | B17: =((Assumptions!C31+Assumptions!C32+Assumptions!C33+Assumptions!C34)*(1+Assumptions!C35)^(1-1)+Assumptions!C30*(1+Assumptions!C36)^(1-1)) | C17: =((Assumptions!D31+Assumptions!D32+Assumptions!D33+Assumptions!D34)*(1+Assumptions!D35)^(1-1)+Assumptions!D30*(1+Assumptions!D36)^(1-1)) | D17: =((Assumptions!E31+Assumptions!E32+Assumptions!E33+Assumptions!E34)*(1+Assumptions!E35)^(1-1)+Assumptions!E30*(1+Assumptions!E36)^(1-1)) | E17: =((Assumptions!C31+Assumptions!C32+Assumptions!C33+Assumptions!C34)*(1+Assumptions!C35)^(2-1)+Assumptions!C30*(1+Assumptions!C36)^(2-1)) | F17: =((Assumptions!D31+Assumptions!D32+Assumptions!D33+Assumptions!D34)*(1+Assumptions!D35)^(2-1)+Assumptions!D30*(1+Assumptions!D36)^(2-1)) | G17: =((Assumptions!E31+Assumptions!E32+Assumptions!E33+Assumptions!E34)*(1+Assumptions!E35)^(2-1)+Assumptions!E30*(1+Assumptions!E36)^(2-1)) | H17: =((Assumptions!C31+Assumptions!C32+Assumptions!C33+Assumptions!C34)*(1+Assumptions!C35)^(3-1)+Assumptions!C30*(1+Assumptions!C36)^(3-1)) | I17: =((Assumptions!D31+Assumptions!D32+Assumptions!D33+Assumptions!D34)*(1+Assumptions!D35)^(3-1)+Assumptions!D30*(1+Assumptions!D36)^(3-1)) | J17: =((Assumptions!E31+Assumptions!E32+Assumptions!E33+Assumptions!E34)*(1+Assumptions!E35)^(3-1)+Assumptions!E30*(1+Assumptions!E36)^(3-1)) | K17: =((Assumptions!C31+Assumptions!C32+Assumptions!C33+Assumptions!C34)*(1+Assumptions!C35)^(4-1)+Assumptions!C30*(1+Assumptions!C36)^(4-1)) | L17: =((Assumptions!D31+Assumptions!D32+Assumptions!D33+Assumptions!D34)*(1+Assumptions!D35)^(4-1)+Assumptions!D30*(1+Assumptions!D36)^(4-1)) | M17: =((Assumptions!E31+Assumptions!E32+Assumptions!E33+Assumptions!E34)*(1+Assumptions!E35)^(4-1)+Assumptions!E30*(1+Assumptions!E36)^(4-1)) | N17: =((Assumptions!C31+Assumptions!C32+Assumptions!C33+Assumptions!C34)*(1+Assumptions!C35)^(5-1)+Assumptions!C30*(1+Assumptions!C36)^(5-1)) | O17: =((Assumptions!D31+Assumptions!D32+Assumptions!D33+Assumptions!D34)*(1+Assumptions!D35)^(5-1)+Assumptions!D30*(1+Assumptions!D36)^(5-1)) | P17: =((Assumptions!E31+Assumptions!E32+Assumptions!E33+Assumptions!E34)*(1+Assumptions!E35)^(5-1)+Assumptions!E30*(1+Assumptions!E36)^(5-1))
A18: Total costs excl. operator payout ($) | B18: =((IF(Assumptions!C17=1,(((Assumptions!C21*(Assumptions!C10*(1+Assumptions!C26)^(1-1)))*(Assumptions!C11+Assumptions!C12))*(1-Assumptions!C20))*Assumptions!C15+Assumptions!C21*Assumptions!C16,(Assumptions!C21*(Assumptions!C10*(1+Assumptions!C26)^(1-1)))*Assumptions!C15+Assumptions!C21*Assumptions!C16))+((Assumptions!C21*(Assumptions!C10*(1+Assumptions!C26)^(1-1)))*Assumptions!C18)+(Assumptions!C21*Assumptions!C19))+(Assumptions!C21*(Assumptions!C28+(Assumptions!C29-Assumptions!C28)*(1-1)/4)*Assumptions!C27)+((Assumptions!C31+Assumptions!C32+Assumptions!C33+Assumptions!C34)*(1+Assumptions!C35)^(1-1)+Assumptions!C30*(1+Assumptions!C36)^(1-1)) | C18: =((IF(Assumptions!D17=1,(((Assumptions!D21*(Assumptions!D10*(1+Assumptions!D26)^(1-1)))*(Assumptions!D11+Assumptions!D12))*(1-Assumptions!D20))*Assumptions!D15+Assumptions!D21*Assumptions!D16,(Assumptions!D21*(Assumptions!D10*(1+Assumptions!D26)^(1-1)))*Assumptions!D15+Assumptions!D21*Assumptions!D16))+((Assumptions!D21*(Assumptions!D10*(1+Assumptions!D26)^(1-1)))*Assumptions!D18)+(Assumptions!D21*Assumptions!D19))+(Assumptions!D21*(Assumptions!D28+(Assumptions!D29-Assumptions!D28)*(1-1)/4)*Assumptions!D27)+((Assumptions!D31+Assumptions!D32+Assumptions!D33+Assumptions!D34)*(1+Assumptions!D35)^(1-1)+Assumptions!D30*(1+Assumptions!D36)^(1-1)) | D18: =((IF(Assumptions!E17=1,(((Assumptions!E21*(Assumptions!E10*(1+Assumptions!E26)^(1-1)))*(Assumptions!E11+Assumptions!E12))*(1-Assumptions!E20))*Assumptions!E15+Assumptions!E21*Assumptions!E16,(Assumptions!E21*(Assumptions!E10*(1+Assumptions!E26)^(1-1)))*Assumptions!E15+Assumptions!E21*Assumptions!E16))+((Assumptions!E21*(Assumptions!E10*(1+Assumptions!E26)^(1-1)))*Assumptions!E18)+(Assumptions!E21*Assumptions!E19))+(Assumptions!E21*(Assumptions!E28+(Assumptions!E29-Assumptions!E28)*(1-1)/4)*Assumptions!E27)+((Assumptions!E31+Assumptions!E32+Assumptions!E33+Assumptions!E34)*(1+Assumptions!E35)^(1-1)+Assumptions!E30*(1+Assumptions!E36)^(1-1)) | E18: =((IF(Assumptions!C17=1,(((Assumptions!C22*(Assumptions!C10*(1+Assumptions!C26)^(2-1)))*(Assumptions!C11+Assumptions!C12))*(1-Assumptions!C20))*Assumptions!C15+Assumptions!C22*Assumptions!C16,(Assumptions!C22*(Assumptions!C10*(1+Assumptions!C26)^(2-1)))*Assumptions!C15+Assumptions!C22*Assumptions!C16))+((Assumptions!C22*(Assumptions!C10*(1+Assumptions!C26)^(2-1)))*Assumptions!C18)+(Assumptions!C22*Assumptions!C19))+(Assumptions!C22*(Assumptions!C28+(Assumptions!C29-Assumptions!C28)*(2-1)/4)*Assumptions!C27)+((Assumptions!C31+Assumptions!C32+Assumptions!C33+Assumptions!C34)*(1+Assumptions!C35)^(2-1)+Assumptions!C30*(1+Assumptions!C36)^(2-1)) | F18: =((IF(Assumptions!D17=1,(((Assumptions!D22*(Assumptions!D10*(1+Assumptions!D26)^(2-1)))*(Assumptions!D11+Assumptions!D12))*(1-Assumptions!D20))*Assumptions!D15+Assumptions!D22*Assumptions!D16,(Assumptions!D22*(Assumptions!D10*(1+Assumptions!D26)^(2-1)))*Assumptions!D15+Assumptions!D22*Assumptions!D16))+((Assumptions!D22*(Assumptions!D10*(1+Assumptions!D26)^(2-1)))*Assumptions!D18)+(Assumptions!D22*Assumptions!D19))+(Assumptions!D22*(Assumptions!D28+(Assumptions!D29-Assumptions!D28)*(2-1)/4)*Assumptions!D27)+((Assumptions!D31+Assumptions!D32+Assumptions!D33+Assumptions!D34)*(1+Assumptions!D35)^(2-1)+Assumptions!D30*(1+Assumptions!D36)^(2-1)) | G18: =((IF(Assumptions!E17=1,(((Assumptions!E22*(Assumptions!E10*(1+Assumptions!E26)^(2-1)))*(Assumptions!E11+Assumptions!E12))*(1-Assumptions!E20))*Assumptions!E15+Assumptions!E22*Assumptions!E16,(Assumptions!E22*(Assumptions!E10*(1+Assumptions!E26)^(2-1)))*Assumptions!E15+Assumptions!E22*Assumptions!E16))+((Assumptions!E22*(Assumptions!E10*(1+Assumptions!E26)^(2-1)))*Assumptions!E18)+(Assumptions!E22*Assumptions!E19))+(Assumptions!E22*(Assumptions!E28+(Assumptions!E29-Assumptions!E28)*(2-1)/4)*Assumptions!E27)+((Assumptions!E31+Assumptions!E32+Assumptions!E33+Assumptions!E34)*(1+Assumptions!E35)^(2-1)+Assumptions!E30*(1+Assumptions!E36)^(2-1)) | H18: =((IF(Assumptions!C17=1,(((Assumptions!C23*(Assumptions!C10*(1+Assumptions!C26)^(3-1)))*(Assumptions!C11+Assumptions!C12))*(1-Assumptions!C20))*Assumptions!C15+Assumptions!C23*Assumptions!C16,(Assumptions!C23*(Assumptions!C10*(1+Assumptions!C26)^(3-1)))*Assumptions!C15+Assumptions!C23*Assumptions!C16))+((Assumptions!C23*(Assumptions!C10*(1+Assumptions!C26)^(3-1)))*Assumptions!C18)+(Assumptions!C23*Assumptions!C19))+(Assumptions!C23*(Assumptions!C28+(Assumptions!C29-Assumptions!C28)*(3-1)/4)*Assumptions!C27)+((Assumptions!C31+Assumptions!C32+Assumptions!C33+Assumptions!C34)*(1+Assumptions!C35)^(3-1)+Assumptions!C30*(1+Assumptions!C36)^(3-1)) | I18: =((IF(Assumptions!D17=1,(((Assumptions!D23*(Assumptions!D10*(1+Assumptions!D26)^(3-1)))*(Assumptions!D11+Assumptions!D12))*(1-Assumptions!D20))*Assumptions!D15+Assumptions!D23*Assumptions!D16,(Assumptions!D23*(Assumptions!D10*(1+Assumptions!D26)^(3-1)))*Assumptions!D15+Assumptions!D23*Assumptions!D16))+((Assumptions!D23*(Assumptions!D10*(1+Assumptions!D26)^(3-1)))*Assumptions!D18)+(Assumptions!D23*Assumptions!D19))+(Assumptions!D23*(Assumptions!D28+(Assumptions!D29-Assumptions!D28)*(3-1)/4)*Assumptions!D27)+((Assumptions!D31+Assumptions!D32+Assumptions!D33+Assumptions!D34)*(1+Assumptions!D35)^(3-1)+Assumptions!D30*(1+Assumptions!D36)^(3-1)) | J18: =((IF(Assumptions!E17=1,(((Assumptions!E23*(Assumptions!E10*(1+Assumptions!E26)^(3-1)))*(Assumptions!E11+Assumptions!E12))*(1-Assumptions!E20))*Assumptions!E15+Assumptions!E23*Assumptions!E16,(Assumptions!E23*(Assumptions!E10*(1+Assumptions!E26)^(3-1)))*Assumptions!E15+Assumptions!E23*Assumptions!E16))+((Assumptions!E23*(Assumptions!E10*(1+Assumptions!E26)^(3-1)))*Assumptions!E18)+(Assumptions!E23*Assumptions!E19))+(Assumptions!E23*(Assumptions!E28+(Assumptions!E29-Assumptions!E28)*(3-1)/4)*Assumptions!E27)+((Assumptions!E31+Assumptions!E32+Assumptions!E33+Assumptions!E34)*(1+Assumptions!E35)^(3-1)+Assumptions!E30*(1+Assumptions!E36)^(3-1)) | K18: =((IF(Assumptions!C17=1,(((Assumptions!C24*(Assumptions!C10*(1+Assumptions!C26)^(4-1)))*(Assumptions!C11+Assumptions!C12))*(1-Assumptions!C20))*Assumptions!C15+Assumptions!C24*Assumptions!C16,(Assumptions!C24*(Assumptions!C10*(1+Assumptions!C26)^(4-1)))*Assumptions!C15+Assumptions!C24*Assumptions!C16))+((Assumptions!C24*(Assumptions!C10*(1+Assumptions!C26)^(4-1)))*Assumptions!C18)+(Assumptions!C24*Assumptions!C19))+(Assumptions!C24*(Assumptions!C28+(Assumptions!C29-Assumptions!C28)*(4-1)/4)*Assumptions!C27)+((Assumptions!C31+Assumptions!C32+Assumptions!C33+Assumptions!C34)*(1+Assumptions!C35)^(4-1)+Assumptions!C30*(1+Assumptions!C36)^(4-1)) | L18: =((IF(Assumptions!D17=1,(((Assumptions!D24*(Assumptions!D10*(1+Assumptions!D26)^(4-1)))*(Assumptions!D11+Assumptions!D12))*(1-Assumptions!D20))*Assumptions!D15+Assumptions!D24*Assumptions!D16,(Assumptions!D24*(Assumptions!D10*(1+Assumptions!D26)^(4-1)))*Assumptions!D15+Assumptions!D24*Assumptions!D16))+((Assumptions!D24*(Assumptions!D10*(1+Assumptions!D26)^(4-1)))*Assumptions!D18)+(Assumptions!D24*Assumptions!D19))+(Assumptions!D24*(Assumptions!D28+(Assumptions!D29-Assumptions!D28)*(4-1)/4)*Assumptions!D27)+((Assumptions!D31+Assumptions!D32+Assumptions!D33+Assumptions!D34)*(1+Assumptions!D35)^(4-1)+Assumptions!D30*(1+Assumptions!D36)^(4-1)) | M18: =((IF(Assumptions!E17=1,(((Assumptions!E24*(Assumptions!E10*(1+Assumptions!E26)^(4-1)))*(Assumptions!E11+Assumptions!E12))*(1-Assumptions!E20))*Assumptions!E15+Assumptions!E24*Assumptions!E16,(Assumptions!E24*(Assumptions!E10*(1+Assumptions!E26)^(4-1)))*Assumptions!E15+Assumptions!E24*Assumptions!E16))+((Assumptions!E24*(Assumptions!E10*(1+Assumptions!E26)^(4-1)))*Assumptions!E18)+(Assumptions!E24*Assumptions!E19))+(Assumptions!E24*(Assumptions!E28+(Assumptions!E29-Assumptions!E28)*(4-1)/4)*Assumptions!E27)+((Assumptions!E31+Assumptions!E32+Assumptions!E33+Assumptions!E34)*(1+Assumptions!E35)^(4-1)+Assumptions!E30*(1+Assumptions!E36)^(4-1)) | N18: =((IF(Assumptions!C17=1,(((Assumptions!C25*(Assumptions!C10*(1+Assumptions!C26)^(5-1)))*(Assumptions!C11+Assumptions!C12))*(1-Assumptions!C20))*Assumptions!C15+Assumptions!C25*Assumptions!C16,(Assumptions!C25*(Assumptions!C10*(1+Assumptions!C26)^(5-1)))*Assumptions!C15+Assumptions!C25*Assumptions!C16))+((Assumptions!C25*(Assumptions!C10*(1+Assumptions!C26)^(5-1)))*Assumptions!C18)+(Assumptions!C25*Assumptions!C19))+(Assumptions!C25*(Assumptions!C28+(Assumptions!C29-Assumptions!C28)*(5-1)/4)*Assumptions!C27)+((Assumptions!C31+Assumptions!C32+Assumptions!C33+Assumptions!C34)*(1+Assumptions!C35)^(5-1)+Assumptions!C30*(1+Assumptions!C36)^(5-1)) | O18: =((IF(Assumptions!D17=1,(((Assumptions!D25*(Assumptions!D10*(1+Assumptions!D26)^(5-1)))*(Assumptions!D11+Assumptions!D12))*(1-Assumptions!D20))*Assumptions!D15+Assumptions!D25*Assumptions!D16,(Assumptions!D25*(Assumptions!D10*(1+Assumptions!D26)^(5-1)))*Assumptions!D15+Assumptions!D25*Assumptions!D16))+((Assumptions!D25*(Assumptions!D10*(1+Assumptions!D26)^(5-1)))*Assumptions!D18)+(Assumptions!D25*Assumptions!D19))+(Assumptions!D25*(Assumptions!D28+(Assumptions!D29-Assumptions!D28)*(5-1)/4)*Assumptions!D27)+((Assumptions!D31+Assumptions!D32+Assumptions!D33+Assumptions!D34)*(1+Assumptions!D35)^(5-1)+Assumptions!D30*(1+Assumptions!D36)^(5-1)) | P18: =((IF(Assumptions!E17=1,(((Assumptions!E25*(Assumptions!E10*(1+Assumptions!E26)^(5-1)))*(Assumptions!E11+Assumptions!E12))*(1-Assumptions!E20))*Assumptions!E15+Assumptions!E25*Assumptions!E16,(Assumptions!E25*(Assumptions!E10*(1+Assumptions!E26)^(5-1)))*Assumptions!E15+Assumptions!E25*Assumptions!E16))+((Assumptions!E25*(Assumptions!E10*(1+Assumptions!E26)^(5-1)))*Assumptions!E18)+(Assumptions!E25*Assumptions!E19))+(Assumptions!E25*(Assumptions!E28+(Assumptions!E29-Assumptions!E28)*(5-1)/4)*Assumptions!E27)+((Assumptions!E31+Assumptions!E32+Assumptions!E33+Assumptions!E34)*(1+Assumptions!E35)^(5-1)+Assumptions!E30*(1+Assumptions!E36)^(5-1))
A19: Net profit / (loss) ($) | B19: =(((((Assumptions!C21*(Assumptions!C10*(1+Assumptions!C26)^(1-1)))*(Assumptions!C11+Assumptions!C12))*(1-Assumptions!C20))-((IF(Assumptions!C17=1,(((Assumptions!C21*(Assumptions!C10*(1+Assumptions!C26)^(1-1)))*(Assumptions!C11+Assumptions!C12))*(1-Assumptions!C20))*Assumptions!C15+Assumptions!C21*Assumptions!C16,(Assumptions!C21*(Assumptions!C10*(1+Assumptions!C26)^(1-1)))*Assumptions!C15+Assumptions!C21*Assumptions!C16))+((Assumptions!C21*(Assumptions!C10*(1+Assumptions!C26)^(1-1)))*Assumptions!C18)+(Assumptions!C21*Assumptions!C19)))-(Assumptions!C21*(Assumptions!C28+(Assumptions!C29-Assumptions!C28)*(1-1)/4)*Assumptions!C27)-((Assumptions!C31+Assumptions!C32+Assumptions!C33+Assumptions!C34)*(1+Assumptions!C35)^(1-1)+Assumptions!C30*(1+Assumptions!C36)^(1-1))) | C19: =(((((Assumptions!D21*(Assumptions!D10*(1+Assumptions!D26)^(1-1)))*(Assumptions!D11+Assumptions!D12))*(1-Assumptions!D20))-((IF(Assumptions!D17=1,(((Assumptions!D21*(Assumptions!D10*(1+Assumptions!D26)^(1-1)))*(Assumptions!D11+Assumptions!D12))*(1-Assumptions!D20))*Assumptions!D15+Assumptions!D21*Assumptions!D16,(Assumptions!D21*(Assumptions!D10*(1+Assumptions!D26)^(1-1)))*Assumptions!D15+Assumptions!D21*Assumptions!D16))+((Assumptions!D21*(Assumptions!D10*(1+Assumptions!D26)^(1-1)))*Assumptions!D18)+(Assumptions!D21*Assumptions!D19)))-(Assumptions!D21*(Assumptions!D28+(Assumptions!D29-Assumptions!D28)*(1-1)/4)*Assumptions!D27)-((Assumptions!D31+Assumptions!D32+Assumptions!D33+Assumptions!D34)*(1+Assumptions!D35)^(1-1)+Assumptions!D30*(1+Assumptions!D36)^(1-1))) | D19: =(((((Assumptions!E21*(Assumptions!E10*(1+Assumptions!E26)^(1-1)))*(Assumptions!E11+Assumptions!E12))*(1-Assumptions!E20))-((IF(Assumptions!E17=1,(((Assumptions!E21*(Assumptions!E10*(1+Assumptions!E26)^(1-1)))*(Assumptions!E11+Assumptions!E12))*(1-Assumptions!E20))*Assumptions!E15+Assumptions!E21*Assumptions!E16,(Assumptions!E21*(Assumptions!E10*(1+Assumptions!E26)^(1-1)))*Assumptions!E15+Assumptions!E21*Assumptions!E16))+((Assumptions!E21*(Assumptions!E10*(1+Assumptions!E26)^(1-1)))*Assumptions!E18)+(Assumptions!E21*Assumptions!E19)))-(Assumptions!E21*(Assumptions!E28+(Assumptions!E29-Assumptions!E28)*(1-1)/4)*Assumptions!E27)-((Assumptions!E31+Assumptions!E32+Assumptions!E33+Assumptions!E34)*(1+Assumptions!E35)^(1-1)+Assumptions!E30*(1+Assumptions!E36)^(1-1))) | E19: =(((((Assumptions!C22*(Assumptions!C10*(1+Assumptions!C26)^(2-1)))*(Assumptions!C11+Assumptions!C12))*(1-Assumptions!C20))-((IF(Assumptions!C17=1,(((Assumptions!C22*(Assumptions!C10*(1+Assumptions!C26)^(2-1)))*(Assumptions!C11+Assumptions!C12))*(1-Assumptions!C20))*Assumptions!C15+Assumptions!C22*Assumptions!C16,(Assumptions!C22*(Assumptions!C10*(1+Assumptions!C26)^(2-1)))*Assumptions!C15+Assumptions!C22*Assumptions!C16))+((Assumptions!C22*(Assumptions!C10*(1+Assumptions!C26)^(2-1)))*Assumptions!C18)+(Assumptions!C22*Assumptions!C19)))-(Assumptions!C22*(Assumptions!C28+(Assumptions!C29-Assumptions!C28)*(2-1)/4)*Assumptions!C27)-((Assumptions!C31+Assumptions!C32+Assumptions!C33+Assumptions!C34)*(1+Assumptions!C35)^(2-1)+Assumptions!C30*(1+Assumptions!C36)^(2-1))) | F19: =(((((Assumptions!D22*(Assumptions!D10*(1+Assumptions!D26)^(2-1)))*(Assumptions!D11+Assumptions!D12))*(1-Assumptions!D20))-((IF(Assumptions!D17=1,(((Assumptions!D22*(Assumptions!D10*(1+Assumptions!D26)^(2-1)))*(Assumptions!D11+Assumptions!D12))*(1-Assumptions!D20))*Assumptions!D15+Assumptions!D22*Assumptions!D16,(Assumptions!D22*(Assumptions!D10*(1+Assumptions!D26)^(2-1)))*Assumptions!D15+Assumptions!D22*Assumptions!D16))+((Assumptions!D22*(Assumptions!D10*(1+Assumptions!D26)^(2-1)))*Assumptions!D18)+(Assumptions!D22*Assumptions!D19)))-(Assumptions!D22*(Assumptions!D28+(Assumptions!D29-Assumptions!D28)*(2-1)/4)*Assumptions!D27)-((Assumptions!D31+Assumptions!D32+Assumptions!D33+Assumptions!D34)*(1+Assumptions!D35)^(2-1)+Assumptions!D30*(1+Assumptions!D36)^(2-1))) | G19: =(((((Assumptions!E22*(Assumptions!E10*(1+Assumptions!E26)^(2-1)))*(Assumptions!E11+Assumptions!E12))*(1-Assumptions!E20))-((IF(Assumptions!E17=1,(((Assumptions!E22*(Assumptions!E10*(1+Assumptions!E26)^(2-1)))*(Assumptions!E11+Assumptions!E12))*(1-Assumptions!E20))*Assumptions!E15+Assumptions!E22*Assumptions!E16,(Assumptions!E22*(Assumptions!E10*(1+Assumptions!E26)^(2-1)))*Assumptions!E15+Assumptions!E22*Assumptions!E16))+((Assumptions!E22*(Assumptions!E10*(1+Assumptions!E26)^(2-1)))*Assumptions!E18)+(Assumptions!E22*Assumptions!E19)))-(Assumptions!E22*(Assumptions!E28+(Assumptions!E29-Assumptions!E28)*(2-1)/4)*Assumptions!E27)-((Assumptions!E31+Assumptions!E32+Assumptions!E33+Assumptions!E34)*(1+Assumptions!E35)^(2-1)+Assumptions!E30*(1+Assumptions!E36)^(2-1))) | H19: =(((((Assumptions!C23*(Assumptions!C10*(1+Assumptions!C26)^(3-1)))*(Assumptions!C11+Assumptions!C12))*(1-Assumptions!C20))-((IF(Assumptions!C17=1,(((Assumptions!C23*(Assumptions!C10*(1+Assumptions!C26)^(3-1)))*(Assumptions!C11+Assumptions!C12))*(1-Assumptions!C20))*Assumptions!C15+Assumptions!C23*Assumptions!C16,(Assumptions!C23*(Assumptions!C10*(1+Assumptions!C26)^(3-1)))*Assumptions!C15+Assumptions!C23*Assumptions!C16))+((Assumptions!C23*(Assumptions!C10*(1+Assumptions!C26)^(3-1)))*Assumptions!C18)+(Assumptions!C23*Assumptions!C19)))-(Assumptions!C23*(Assumptions!C28+(Assumptions!C29-Assumptions!C28)*(3-1)/4)*Assumptions!C27)-((Assumptions!C31+Assumptions!C32+Assumptions!C33+Assumptions!C34)*(1+Assumptions!C35)^(3-1)+Assumptions!C30*(1+Assumptions!C36)^(3-1))) | I19: =(((((Assumptions!D23*(Assumptions!D10*(1+Assumptions!D26)^(3-1)))*(Assumptions!D11+Assumptions!D12))*(1-Assumptions!D20))-((IF(Assumptions!D17=1,(((Assumptions!D23*(Assumptions!D10*(1+Assumptions!D26)^(3-1)))*(Assumptions!D11+Assumptions!D12))*(1-Assumptions!D20))*Assumptions!D15+Assumptions!D23*Assumptions!D16,(Assumptions!D23*(Assumptions!D10*(1+Assumptions!D26)^(3-1)))*Assumptions!D15+Assumptions!D23*Assumptions!D16))+((Assumptions!D23*(Assumptions!D10*(1+Assumptions!D26)^(3-1)))*Assumptions!D18)+(Assumptions!D23*Assumptions!D19)))-(Assumptions!D23*(Assumptions!D28+(Assumptions!D29-Assumptions!D28)*(3-1)/4)*Assumptions!D27)-((Assumptions!D31+Assumptions!D32+Assumptions!D33+Assumptions!D34)*(1+Assumptions!D35)^(3-1)+Assumptions!D30*(1+Assumptions!D36)^(3-1))) | J19: =(((((Assumptions!E23*(Assumptions!E10*(1+Assumptions!E26)^(3-1)))*(Assumptions!E11+Assumptions!E12))*(1-Assumptions!E20))-((IF(Assumptions!E17=1,(((Assumptions!E23*(Assumptions!E10*(1+Assumptions!E26)^(3-1)))*(Assumptions!E11+Assumptions!E12))*(1-Assumptions!E20))*Assumptions!E15+Assumptions!E23*Assumptions!E16,(Assumptions!E23*(Assumptions!E10*(1+Assumptions!E26)^(3-1)))*Assumptions!E15+Assumptions!E23*Assumptions!E16))+((Assumptions!E23*(Assumptions!E10*(1+Assumptions!E26)^(3-1)))*Assumptions!E18)+(Assumptions!E23*Assumptions!E19)))-(Assumptions!E23*(Assumptions!E28+(Assumptions!E29-Assumptions!E28)*(3-1)/4)*Assumptions!E27)-((Assumptions!E31+Assumptions!E32+Assumptions!E33+Assumptions!E34)*(1+Assumptions!E35)^(3-1)+Assumptions!E30*(1+Assumptions!E36)^(3-1))) | K19: =(((((Assumptions!C24*(Assumptions!C10*(1+Assumptions!C26)^(4-1)))*(Assumptions!C11+Assumptions!C12))*(1-Assumptions!C20))-((IF(Assumptions!C17=1,(((Assumptions!C24*(Assumptions!C10*(1+Assumptions!C26)^(4-1)))*(Assumptions!C11+Assumptions!C12))*(1-Assumptions!C20))*Assumptions!C15+Assumptions!C24*Assumptions!C16,(Assumptions!C24*(Assumptions!C10*(1+Assumptions!C26)^(4-1)))*Assumptions!C15+Assumptions!C24*Assumptions!C16))+((Assumptions!C24*(Assumptions!C10*(1+Assumptions!C26)^(4-1)))*Assumptions!C18)+(Assumptions!C24*Assumptions!C19)))-(Assumptions!C24*(Assumptions!C28+(Assumptions!C29-Assumptions!C28)*(4-1)/4)*Assumptions!C27)-((Assumptions!C31+Assumptions!C32+Assumptions!C33+Assumptions!C34)*(1+Assumptions!C35)^(4-1)+Assumptions!C30*(1+Assumptions!C36)^(4-1))) | L19: =(((((Assumptions!D24*(Assumptions!D10*(1+Assumptions!D26)^(4-1)))*(Assumptions!D11+Assumptions!D12))*(1-Assumptions!D20))-((IF(Assumptions!D17=1,(((Assumptions!D24*(Assumptions!D10*(1+Assumptions!D26)^(4-1)))*(Assumptions!D11+Assumptions!D12))*(1-Assumptions!D20))*Assumptions!D15+Assumptions!D24*Assumptions!D16,(Assumptions!D24*(Assumptions!D10*(1+Assumptions!D26)^(4-1)))*Assumptions!D15+Assumptions!D24*Assumptions!D16))+((Assumptions!D24*(Assumptions!D10*(1+Assumptions!D26)^(4-1)))*Assumptions!D18)+(Assumptions!D24*Assumptions!D19)))-(Assumptions!D24*(Assumptions!D28+(Assumptions!D29-Assumptions!D28)*(4-1)/4)*Assumptions!D27)-((Assumptions!D31+Assumptions!D32+Assumptions!D33+Assumptions!D34)*(1+Assumptions!D35)^(4-1)+Assumptions!D30*(1+Assumptions!D36)^(4-1))) | M19: =(((((Assumptions!E24*(Assumptions!E10*(1+Assumptions!E26)^(4-1)))*(Assumptions!E11+Assumptions!E12))*(1-Assumptions!E20))-((IF(Assumptions!E17=1,(((Assumptions!E24*(Assumptions!E10*(1+Assumptions!E26)^(4-1)))*(Assumptions!E11+Assumptions!E12))*(1-Assumptions!E20))*Assumptions!E15+Assumptions!E24*Assumptions!E16,(Assumptions!E24*(Assumptions!E10*(1+Assumptions!E26)^(4-1)))*Assumptions!E15+Assumptions!E24*Assumptions!E16))+((Assumptions!E24*(Assumptions!E10*(1+Assumptions!E26)^(4-1)))*Assumptions!E18)+(Assumptions!E24*Assumptions!E19)))-(Assumptions!E24*(Assumptions!E28+(Assumptions!E29-Assumptions!E28)*(4-1)/4)*Assumptions!E27)-((Assumptions!E31+Assumptions!E32+Assumptions!E33+Assumptions!E34)*(1+Assumptions!E35)^(4-1)+Assumptions!E30*(1+Assumptions!E36)^(4-1))) | N19: =(((((Assumptions!C25*(Assumptions!C10*(1+Assumptions!C26)^(5-1)))*(Assumptions!C11+Assumptions!C12))*(1-Assumptions!C20))-((IF(Assumptions!C17=1,(((Assumptions!C25*(Assumptions!C10*(1+Assumptions!C26)^(5-1)))*(Assumptions!C11+Assumptions!C12))*(1-Assumptions!C20))*Assumptions!C15+Assumptions!C25*Assumptions!C16,(Assumptions!C25*(Assumptions!C10*(1+Assumptions!C26)^(5-1)))*Assumptions!C15+Assumptions!C25*Assumptions!C16))+((Assumptions!C25*(Assumptions!C10*(1+Assumptions!C26)^(5-1)))*Assumptions!C18)+(Assumptions!C25*Assumptions!C19)))-(Assumptions!C25*(Assumptions!C28+(Assumptions!C29-Assumptions!C28)*(5-1)/4)*Assumptions!C27)-((Assumptions!C31+Assumptions!C32+Assumptions!C33+Assumptions!C34)*(1+Assumptions!C35)^(5-1)+Assumptions!C30*(1+Assumptions!C36)^(5-1))) | O19: =(((((Assumptions!D25*(Assumptions!D10*(1+Assumptions!D26)^(5-1)))*(Assumptions!D11+Assumptions!D12))*(1-Assumptions!D20))-((IF(Assumptions!D17=1,(((Assumptions!D25*(Assumptions!D10*(1+Assumptions!D26)^(5-1)))*(Assumptions!D11+Assumptions!D12))*(1-Assumptions!D20))*Assumptions!D15+Assumptions!D25*Assumptions!D16,(Assumptions!D25*(Assumptions!D10*(1+Assumptions!D26)^(5-1)))*Assumptions!D15+Assumptions!D25*Assumptions!D16))+((Assumptions!D25*(Assumptions!D10*(1+Assumptions!D26)^(5-1)))*Assumptions!D18)+(Assumptions!D25*Assumptions!D19)))-(Assumptions!D25*(Assumptions!D28+(Assumptions!D29-Assumptions!D28)*(5-1)/4)*Assumptions!D27)-((Assumptions!D31+Assumptions!D32+Assumptions!D33+Assumptions!D34)*(1+Assumptions!D35)^(5-1)+Assumptions!D30*(1+Assumptions!D36)^(5-1))) | P19: =(((((Assumptions!E25*(Assumptions!E10*(1+Assumptions!E26)^(5-1)))*(Assumptions!E11+Assumptions!E12))*(1-Assumptions!E20))-((IF(Assumptions!E17=1,(((Assumptions!E25*(Assumptions!E10*(1+Assumptions!E26)^(5-1)))*(Assumptions!E11+Assumptions!E12))*(1-Assumptions!E20))*Assumptions!E15+Assumptions!E25*Assumptions!E16,(Assumptions!E25*(Assumptions!E10*(1+Assumptions!E26)^(5-1)))*Assumptions!E15+Assumptions!E25*Assumptions!E16))+((Assumptions!E25*(Assumptions!E10*(1+Assumptions!E26)^(5-1)))*Assumptions!E18)+(Assumptions!E25*Assumptions!E19)))-(Assumptions!E25*(Assumptions!E28+(Assumptions!E29-Assumptions!E28)*(5-1)/4)*Assumptions!E27)-((Assumptions!E31+Assumptions!E32+Assumptions!E33+Assumptions!E34)*(1+Assumptions!E35)^(5-1)+Assumptions!E30*(1+Assumptions!E36)^(5-1)))
A20: Net margin % of platform revenue | B20: =IF((((Assumptions!C21*(Assumptions!C10*(1+Assumptions!C26)^(1-1)))*(Assumptions!C11+Assumptions!C12))*(1-Assumptions!C20))=0,0,(((((Assumptions!C21*(Assumptions!C10*(1+Assumptions!C26)^(1-1)))*(Assumptions!C11+Assumptions!C12))*(1-Assumptions!C20))-((IF(Assumptions!C17=1,(((Assumptions!C21*(Assumptions!C10*(1+Assumptions!C26)^(1-1)))*(Assumptions!C11+Assumptions!C12))*(1-Assumptions!C20))*Assumptions!C15+Assumptions!C21*Assumptions!C16,(Assumptions!C21*(Assumptions!C10*(1+Assumptions!C26)^(1-1)))*Assumptions!C15+Assumptions!C21*Assumptions!C16))+((Assumptions!C21*(Assumptions!C10*(1+Assumptions!C26)^(1-1)))*Assumptions!C18)+(Assumptions!C21*Assumptions!C19)))-(Assumptions!C21*(Assumptions!C28+(Assumptions!C29-Assumptions!C28)*(1-1)/4)*Assumptions!C27)-((Assumptions!C31+Assumptions!C32+Assumptions!C33+Assumptions!C34)*(1+Assumptions!C35)^(1-1)+Assumptions!C30*(1+Assumptions!C36)^(1-1)))/(((Assumptions!C21*(Assumptions!C10*(1+Assumptions!C26)^(1-1)))*(Assumptions!C11+Assumptions!C12))*(1-Assumptions!C20))) | C20: =IF((((Assumptions!D21*(Assumptions!D10*(1+Assumptions!D26)^(1-1)))*(Assumptions!D11+Assumptions!D12))*(1-Assumptions!D20))=0,0,(((((Assumptions!D21*(Assumptions!D10*(1+Assumptions!D26)^(1-1)))*(Assumptions!D11+Assumptions!D12))*(1-Assumptions!D20))-((IF(Assumptions!D17=1,(((Assumptions!D21*(Assumptions!D10*(1+Assumptions!D26)^(1-1)))*(Assumptions!D11+Assumptions!D12))*(1-Assumptions!D20))*Assumptions!D15+Assumptions!D21*Assumptions!D16,(Assumptions!D21*(Assumptions!D10*(1+Assumptions!D26)^(1-1)))*Assumptions!D15+Assumptions!D21*Assumptions!D16))+((Assumptions!D21*(Assumptions!D10*(1+Assumptions!D26)^(1-1)))*Assumptions!D18)+(Assumptions!D21*Assumptions!D19)))-(Assumptions!D21*(Assumptions!D28+(Assumptions!D29-Assumptions!D28)*(1-1)/4)*Assumptions!D27)-((Assumptions!D31+Assumptions!D32+Assumptions!D33+Assumptions!D34)*(1+Assumptions!D35)^(1-1)+Assumptions!D30*(1+Assumptions!D36)^(1-1)))/(((Assumptions!D21*(Assumptions!D10*(1+Assumptions!D26)^(1-1)))*(Assumptions!D11+Assumptions!D12))*(1-Assumptions!D20))) | D20: =IF((((Assumptions!E21*(Assumptions!E10*(1+Assumptions!E26)^(1-1)))*(Assumptions!E11+Assumptions!E12))*(1-Assumptions!E20))=0,0,(((((Assumptions!E21*(Assumptions!E10*(1+Assumptions!E26)^(1-1)))*(Assumptions!E11+Assumptions!E12))*(1-Assumptions!E20))-((IF(Assumptions!E17=1,(((Assumptions!E21*(Assumptions!E10*(1+Assumptions!E26)^(1-1)))*(Assumptions!E11+Assumptions!E12))*(1-Assumptions!E20))*Assumptions!E15+Assumptions!E21*Assumptions!E16,(Assumptions!E21*(Assumptions!E10*(1+Assumptions!E26)^(1-1)))*Assumptions!E15+Assumptions!E21*Assumptions!E16))+((Assumptions!E21*(Assumptions!E10*(1+Assumptions!E26)^(1-1)))*Assumptions!E18)+(Assumptions!E21*Assumptions!E19)))-(Assumptions!E21*(Assumptions!E28+(Assumptions!E29-Assumptions!E28)*(1-1)/4)*Assumptions!E27)-((Assumptions!E31+Assumptions!E32+Assumptions!E33+Assumptions!E34)*(1+Assumptions!E35)^(1-1)+Assumptions!E30*(1+Assumptions!E36)^(1-1)))/(((Assumptions!E21*(Assumptions!E10*(1+Assumptions!E26)^(1-1)))*(Assumptions!E11+Assumptions!E12))*(1-Assumptions!E20))) | E20: =IF((((Assumptions!C22*(Assumptions!C10*(1+Assumptions!C26)^(2-1)))*(Assumptions!C11+Assumptions!C12))*(1-Assumptions!C20))=0,0,(((((Assumptions!C22*(Assumptions!C10*(1+Assumptions!C26)^(2-1)))*(Assumptions!C11+Assumptions!C12))*(1-Assumptions!C20))-((IF(Assumptions!C17=1,(((Assumptions!C22*(Assumptions!C10*(1+Assumptions!C26)^(2-1)))*(Assumptions!C11+Assumptions!C12))*(1-Assumptions!C20))*Assumptions!C15+Assumptions!C22*Assumptions!C16,(Assumptions!C22*(Assumptions!C10*(1+Assumptions!C26)^(2-1)))*Assumptions!C15+Assumptions!C22*Assumptions!C16))+((Assumptions!C22*(Assumptions!C10*(1+Assumptions!C26)^(2-1)))*Assumptions!C18)+(Assumptions!C22*Assumptions!C19)))-(Assumptions!C22*(Assumptions!C28+(Assumptions!C29-Assumptions!C28)*(2-1)/4)*Assumptions!C27)-((Assumptions!C31+Assumptions!C32+Assumptions!C33+Assumptions!C34)*(1+Assumptions!C35)^(2-1)+Assumptions!C30*(1+Assumptions!C36)^(2-1)))/(((Assumptions!C22*(Assumptions!C10*(1+Assumptions!C26)^(2-1)))*(Assumptions!C11+Assumptions!C12))*(1-Assumptions!C20))) | F20: =IF((((Assumptions!D22*(Assumptions!D10*(1+Assumptions!D26)^(2-1)))*(Assumptions!D11+Assumptions!D12))*(1-Assumptions!D20))=0,0,(((((Assumptions!D22*(Assumptions!D10*(1+Assumptions!D26)^(2-1)))*(Assumptions!D11+Assumptions!D12))*(1-Assumptions!D20))-((IF(Assumptions!D17=1,(((Assumptions!D22*(Assumptions!D10*(1+Assumptions!D26)^(2-1)))*(Assumptions!D11+Assumptions!D12))*(1-Assumptions!D20))*Assumptions!D15+Assumptions!D22*Assumptions!D16,(Assumptions!D22*(Assumptions!D10*(1+Assumptions!D26)^(2-1)))*Assumptions!D15+Assumptions!D22*Assumptions!D16))+((Assumptions!D22*(Assumptions!D10*(1+Assumptions!D26)^(2-1)))*Assumptions!D18)+(Assumptions!D22*Assumptions!D19)))-(Assumptions!D22*(Assumptions!D28+(Assumptions!D29-Assumptions!D28)*(2-1)/4)*Assumptions!D27)-((Assumptions!D31+Assumptions!D32+Assumptions!D33+Assumptions!D34)*(1+Assumptions!D35)^(2-1)+Assumptions!D30*(1+Assumptions!D36)^(2-1)))/(((Assumptions!D22*(Assumptions!D10*(1+Assumptions!D26)^(2-1)))*(Assumptions!D11+Assumptions!D12))*(1-Assumptions!D20))) | G20: =IF((((Assumptions!E22*(Assumptions!E10*(1+Assumptions!E26)^(2-1)))*(Assumptions!E11+Assumptions!E12))*(1-Assumptions!E20))=0,0,(((((Assumptions!E22*(Assumptions!E10*(1+Assumptions!E26)^(2-1)))*(Assumptions!E11+Assumptions!E12))*(1-Assumptions!E20))-((IF(Assumptions!E17=1,(((Assumptions!E22*(Assumptions!E10*(1+Assumptions!E26)^(2-1)))*(Assumptions!E11+Assumptions!E12))*(1-Assumptions!E20))*Assumptions!E15+Assumptions!E22*Assumptions!E16,(Assumptions!E22*(Assumptions!E10*(1+Assumptions!E26)^(2-1)))*Assumptions!E15+Assumptions!E22*Assumptions!E16))+((Assumptions!E22*(Assumptions!E10*(1+Assumptions!E26)^(2-1)))*Assumptions!E18)+(Assumptions!E22*Assumptions!E19)))-(Assumptions!E22*(Assumptions!E28+(Assumptions!E29-Assumptions!E28)*(2-1)/4)*Assumptions!E27)-((Assumptions!E31+Assumptions!E32+Assumptions!E33+Assumptions!E34)*(1+Assumptions!E35)^(2-1)+Assumptions!E30*(1+Assumptions!E36)^(2-1)))/(((Assumptions!E22*(Assumptions!E10*(1+Assumptions!E26)^(2-1)))*(Assumptions!E11+Assumptions!E12))*(1-Assumptions!E20))) | H20: =IF((((Assumptions!C23*(Assumptions!C10*(1+Assumptions!C26)^(3-1)))*(Assumptions!C11+Assumptions!C12))*(1-Assumptions!C20))=0,0,(((((Assumptions!C23*(Assumptions!C10*(1+Assumptions!C26)^(3-1)))*(Assumptions!C11+Assumptions!C12))*(1-Assumptions!C20))-((IF(Assumptions!C17=1,(((Assumptions!C23*(Assumptions!C10*(1+Assumptions!C26)^(3-1)))*(Assumptions!C11+Assumptions!C12))*(1-Assumptions!C20))*Assumptions!C15+Assumptions!C23*Assumptions!C16,(Assumptions!C23*(Assumptions!C10*(1+Assumptions!C26)^(3-1)))*Assumptions!C15+Assumptions!C23*Assumptions!C16))+((Assumptions!C23*(Assumptions!C10*(1+Assumptions!C26)^(3-1)))*Assumptions!C18)+(Assumptions!C23*Assumptions!C19)))-(Assumptions!C23*(Assumptions!C28+(Assumptions!C29-Assumptions!C28)*(3-1)/4)*Assumptions!C27)-((Assumptions!C31+Assumptions!C32+Assumptions!C33+Assumptions!C34)*(1+Assumptions!C35)^(3-1)+Assumptions!C30*(1+Assumptions!C36)^(3-1)))/(((Assumptions!C23*(Assumptions!C10*(1+Assumptions!C26)^(3-1)))*(Assumptions!C11+Assumptions!C12))*(1-Assumptions!C20))) | I20: =IF((((Assumptions!D23*(Assumptions!D10*(1+Assumptions!D26)^(3-1)))*(Assumptions!D11+Assumptions!D12))*(1-Assumptions!D20))=0,0,(((((Assumptions!D23*(Assumptions!D10*(1+Assumptions!D26)^(3-1)))*(Assumptions!D11+Assumptions!D12))*(1-Assumptions!D20))-((IF(Assumptions!D17=1,(((Assumptions!D23*(Assumptions!D10*(1+Assumptions!D26)^(3-1)))*(Assumptions!D11+Assumptions!D12))*(1-Assumptions!D20))*Assumptions!D15+Assumptions!D23*Assumptions!D16,(Assumptions!D23*(Assumptions!D10*(1+Assumptions!D26)^(3-1)))*Assumptions!D15+Assumptions!D23*Assumptions!D16))+((Assumptions!D23*(Assumptions!D10*(1+Assumptions!D26)^(3-1)))*Assumptions!D18)+(Assumptions!D23*Assumptions!D19)))-(Assumptions!D23*(Assumptions!D28+(Assumptions!D29-Assumptions!D28)*(3-1)/4)*Assumptions!D27)-((Assumptions!D31+Assumptions!D32+Assumptions!D33+Assumptions!D34)*(1+Assumptions!D35)^(3-1)+Assumptions!D30*(1+Assumptions!D36)^(3-1)))/(((Assumptions!D23*(Assumptions!D10*(1+Assumptions!D26)^(3-1)))*(Assumptions!D11+Assumptions!D12))*(1-Assumptions!D20))) | J20: =IF((((Assumptions!E23*(Assumptions!E10*(1+Assumptions!E26)^(3-1)))*(Assumptions!E11+Assumptions!E12))*(1-Assumptions!E20))=0,0,(((((Assumptions!E23*(Assumptions!E10*(1+Assumptions!E26)^(3-1)))*(Assumptions!E11+Assumptions!E12))*(1-Assumptions!E20))-((IF(Assumptions!E17=1,(((Assumptions!E23*(Assumptions!E10*(1+Assumptions!E26)^(3-1)))*(Assumptions!E11+Assumptions!E12))*(1-Assumptions!E20))*Assumptions!E15+Assumptions!E23*Assumptions!E16,(Assumptions!E23*(Assumptions!E10*(1+Assumptions!E26)^(3-1)))*Assumptions!E15+Assumptions!E23*Assumptions!E16))+((Assumptions!E23*(Assumptions!E10*(1+Assumptions!E26)^(3-1)))*Assumptions!E18)+(Assumptions!E23*Assumptions!E19)))-(Assumptions!E23*(Assumptions!E28+(Assumptions!E29-Assumptions!E28)*(3-1)/4)*Assumptions!E27)-((Assumptions!E31+Assumptions!E32+Assumptions!E33+Assumptions!E34)*(1+Assumptions!E35)^(3-1)+Assumptions!E30*(1+Assumptions!E36)^(3-1)))/(((Assumptions!E23*(Assumptions!E10*(1+Assumptions!E26)^(3-1)))*(Assumptions!E11+Assumptions!E12))*(1-Assumptions!E20))) | K20: =IF((((Assumptions!C24*(Assumptions!C10*(1+Assumptions!C26)^(4-1)))*(Assumptions!C11+Assumptions!C12))*(1-Assumptions!C20))=0,0,(((((Assumptions!C24*(Assumptions!C10*(1+Assumptions!C26)^(4-1)))*(Assumptions!C11+Assumptions!C12))*(1-Assumptions!C20))-((IF(Assumptions!C17=1,(((Assumptions!C24*(Assumptions!C10*(1+Assumptions!C26)^(4-1)))*(Assumptions!C11+Assumptions!C12))*(1-Assumptions!C20))*Assumptions!C15+Assumptions!C24*Assumptions!C16,(Assumptions!C24*(Assumptions!C10*(1+Assumptions!C26)^(4-1)))*Assumptions!C15+Assumptions!C24*Assumptions!C16))+((Assumptions!C24*(Assumptions!C10*(1+Assumptions!C26)^(4-1)))*Assumptions!C18)+(Assumptions!C24*Assumptions!C19)))-(Assumptions!C24*(Assumptions!C28+(Assumptions!C29-Assumptions!C28)*(4-1)/4)*Assumptions!C27)-((Assumptions!C31+Assumptions!C32+Assumptions!C33+Assumptions!C34)*(1+Assumptions!C35)^(4-1)+Assumptions!C30*(1+Assumptions!C36)^(4-1)))/(((Assumptions!C24*(Assumptions!C10*(1+Assumptions!C26)^(4-1)))*(Assumptions!C11+Assumptions!C12))*(1-Assumptions!C20))) | L20: =IF((((Assumptions!D24*(Assumptions!D10*(1+Assumptions!D26)^(4-1)))*(Assumptions!D11+Assumptions!D12))*(1-Assumptions!D20))=0,0,(((((Assumptions!D24*(Assumptions!D10*(1+Assumptions!D26)^(4-1)))*(Assumptions!D11+Assumptions!D12))*(1-Assumptions!D20))-((IF(Assumptions!D17=1,(((Assumptions!D24*(Assumptions!D10*(1+Assumptions!D26)^(4-1)))*(Assumptions!D11+Assumptions!D12))*(1-Assumptions!D20))*Assumptions!D15+Assumptions!D24*Assumptions!D16,(Assumptions!D24*(Assumptions!D10*(1+Assumptions!D26)^(4-1)))*Assumptions!D15+Assumptions!D24*Assumptions!D16))+((Assumptions!D24*(Assumptions!D10*(1+Assumptions!D26)^(4-1)))*Assumptions!D18)+(Assumptions!D24*Assumptions!D19)))-(Assumptions!D24*(Assumptions!D28+(Assumptions!D29-Assumptions!D28)*(4-1)/4)*Assumptions!D27)-((Assumptions!D31+Assumptions!D32+Assumptions!D33+Assumptions!D34)*(1+Assumptions!D35)^(4-1)+Assumptions!D30*(1+Assumptions!D36)^(4-1)))/(((Assumptions!D24*(Assumptions!D10*(1+Assumptions!D26)^(4-1)))*(Assumptions!D11+Assumptions!D12))*(1-Assumptions!D20))) | M20: =IF((((Assumptions!E24*(Assumptions!E10*(1+Assumptions!E26)^(4-1)))*(Assumptions!E11+Assumptions!E12))*(1-Assumptions!E20))=0,0,(((((Assumptions!E24*(Assumptions!E10*(1+Assumptions!E26)^(4-1)))*(Assumptions!E11+Assumptions!E12))*(1-Assumptions!E20))-((IF(Assumptions!E17=1,(((Assumptions!E24*(Assumptions!E10*(1+Assumptions!E26)^(4-1)))*(Assumptions!E11+Assumptions!E12))*(1-Assumptions!E20))*Assumptions!E15+Assumptions!E24*Assumptions!E16,(Assumptions!E24*(Assumptions!E10*(1+Assumptions!E26)^(4-1)))*Assumptions!E15+Assumptions!E24*Assumptions!E16))+((Assumptions!E24*(Assumptions!E10*(1+Assumptions!E26)^(4-1)))*Assumptions!E18)+(Assumptions!E24*Assumptions!E19)))-(Assumptions!E24*(Assumptions!E28+(Assumptions!E29-Assumptions!E28)*(4-1)/4)*Assumptions!E27)-((Assumptions!E31+Assumptions!E32+Assumptions!E33+Assumptions!E34)*(1+Assumptions!E35)^(4-1)+Assumptions!E30*(1+Assumptions!E36)^(4-1)))/(((Assumptions!E24*(Assumptions!E10*(1+Assumptions!E26)^(4-1)))*(Assumptions!E11+Assumptions!E12))*(1-Assumptions!E20))) | N20: =IF((((Assumptions!C25*(Assumptions!C10*(1+Assumptions!C26)^(5-1)))*(Assumptions!C11+Assumptions!C12))*(1-Assumptions!C20))=0,0,(((((Assumptions!C25*(Assumptions!C10*(1+Assumptions!C26)^(5-1)))*(Assumptions!C11+Assumptions!C12))*(1-Assumptions!C20))-((IF(Assumptions!C17=1,(((Assumptions!C25*(Assumptions!C10*(1+Assumptions!C26)^(5-1)))*(Assumptions!C11+Assumptions!C12))*(1-Assumptions!C20))*Assumptions!C15+Assumptions!C25*Assumptions!C16,(Assumptions!C25*(Assumptions!C10*(1+Assumptions!C26)^(5-1)))*Assumptions!C15+Assumptions!C25*Assumptions!C16))+((Assumptions!C25*(Assumptions!C10*(1+Assumptions!C26)^(5-1)))*Assumptions!C18)+(Assumptions!C25*Assumptions!C19)))-(Assumptions!C25*(Assumptions!C28+(Assumptions!C29-Assumptions!C28)*(5-1)/4)*Assumptions!C27)-((Assumptions!C31+Assumptions!C32+Assumptions!C33+Assumptions!C34)*(1+Assumptions!C35)^(5-1)+Assumptions!C30*(1+Assumptions!C36)^(5-1)))/(((Assumptions!C25*(Assumptions!C10*(1+Assumptions!C26)^(5-1)))*(Assumptions!C11+Assumptions!C12))*(1-Assumptions!C20))) | O20: =IF((((Assumptions!D25*(Assumptions!D10*(1+Assumptions!D26)^(5-1)))*(Assumptions!D11+Assumptions!D12))*(1-Assumptions!D20))=0,0,(((((Assumptions!D25*(Assumptions!D10*(1+Assumptions!D26)^(5-1)))*(Assumptions!D11+Assumptions!D12))*(1-Assumptions!D20))-((IF(Assumptions!D17=1,(((Assumptions!D25*(Assumptions!D10*(1+Assumptions!D26)^(5-1)))*(Assumptions!D11+Assumptions!D12))*(1-Assumptions!D20))*Assumptions!D15+Assumptions!D25*Assumptions!D16,(Assumptions!D25*(Assumptions!D10*(1+Assumptions!D26)^(5-1)))*Assumptions!D15+Assumptions!D25*Assumptions!D16))+((Assumptions!D25*(Assumptions!D10*(1+Assumptions!D26)^(5-1)))*Assumptions!D18)+(Assumptions!D25*Assumptions!D19)))-(Assumptions!D25*(Assumptions!D28+(Assumptions!D29-Assumptions!D28)*(5-1)/4)*Assumptions!D27)-((Assumptions!D31+Assumptions!D32+Assumptions!D33+Assumptions!D34)*(1+Assumptions!D35)^(5-1)+Assumptions!D30*(1+Assumptions!D36)^(5-1)))/(((Assumptions!D25*(Assumptions!D10*(1+Assumptions!D26)^(5-1)))*(Assumptions!D11+Assumptions!D12))*(1-Assumptions!D20))) | P20: =IF((((Assumptions!E25*(Assumptions!E10*(1+Assumptions!E26)^(5-1)))*(Assumptions!E11+Assumptions!E12))*(1-Assumptions!E20))=0,0,(((((Assumptions!E25*(Assumptions!E10*(1+Assumptions!E26)^(5-1)))*(Assumptions!E11+Assumptions!E12))*(1-Assumptions!E20))-((IF(Assumptions!E17=1,(((Assumptions!E25*(Assumptions!E10*(1+Assumptions!E26)^(5-1)))*(Assumptions!E11+Assumptions!E12))*(1-Assumptions!E20))*Assumptions!E15+Assumptions!E25*Assumptions!E16,(Assumptions!E25*(Assumptions!E10*(1+Assumptions!E26)^(5-1)))*Assumptions!E15+Assumptions!E25*Assumptions!E16))+((Assumptions!E25*(Assumptions!E10*(1+Assumptions!E26)^(5-1)))*Assumptions!E18)+(Assumptions!E25*Assumptions!E19)))-(Assumptions!E25*(Assumptions!E28+(Assumptions!E29-Assumptions!E28)*(5-1)/4)*Assumptions!E27)-((Assumptions!E31+Assumptions!E32+Assumptions!E33+Assumptions!E34)*(1+Assumptions!E35)^(5-1)+Assumptions!E30*(1+Assumptions!E36)^(5-1)))/(((Assumptions!E25*(Assumptions!E10*(1+Assumptions!E26)^(5-1)))*(Assumptions!E11+Assumptions!E12))*(1-Assumptions!E20)))
A21: Platform revenue per booking ($) | B21: =(((Assumptions!C21*(Assumptions!C10*(1+Assumptions!C26)^(1-1)))*(Assumptions!C11+Assumptions!C12))*(1-Assumptions!C20))/Assumptions!C21 | C21: =(((Assumptions!D21*(Assumptions!D10*(1+Assumptions!D26)^(1-1)))*(Assumptions!D11+Assumptions!D12))*(1-Assumptions!D20))/Assumptions!D21 | D21: =(((Assumptions!E21*(Assumptions!E10*(1+Assumptions!E26)^(1-1)))*(Assumptions!E11+Assumptions!E12))*(1-Assumptions!E20))/Assumptions!E21 | E21: =(((Assumptions!C22*(Assumptions!C10*(1+Assumptions!C26)^(2-1)))*(Assumptions!C11+Assumptions!C12))*(1-Assumptions!C20))/Assumptions!C22 | F21: =(((Assumptions!D22*(Assumptions!D10*(1+Assumptions!D26)^(2-1)))*(Assumptions!D11+Assumptions!D12))*(1-Assumptions!D20))/Assumptions!D22 | G21: =(((Assumptions!E22*(Assumptions!E10*(1+Assumptions!E26)^(2-1)))*(Assumptions!E11+Assumptions!E12))*(1-Assumptions!E20))/Assumptions!E22 | H21: =(((Assumptions!C23*(Assumptions!C10*(1+Assumptions!C26)^(3-1)))*(Assumptions!C11+Assumptions!C12))*(1-Assumptions!C20))/Assumptions!C23 | I21: =(((Assumptions!D23*(Assumptions!D10*(1+Assumptions!D26)^(3-1)))*(Assumptions!D11+Assumptions!D12))*(1-Assumptions!D20))/Assumptions!D23 | J21: =(((Assumptions!E23*(Assumptions!E10*(1+Assumptions!E26)^(3-1)))*(Assumptions!E11+Assumptions!E12))*(1-Assumptions!E20))/Assumptions!E23 | K21: =(((Assumptions!C24*(Assumptions!C10*(1+Assumptions!C26)^(4-1)))*(Assumptions!C11+Assumptions!C12))*(1-Assumptions!C20))/Assumptions!C24 | L21: =(((Assumptions!D24*(Assumptions!D10*(1+Assumptions!D26)^(4-1)))*(Assumptions!D11+Assumptions!D12))*(1-Assumptions!D20))/Assumptions!D24 | M21: =(((Assumptions!E24*(Assumptions!E10*(1+Assumptions!E26)^(4-1)))*(Assumptions!E11+Assumptions!E12))*(1-Assumptions!E20))/Assumptions!E24 | N21: =(((Assumptions!C25*(Assumptions!C10*(1+Assumptions!C26)^(5-1)))*(Assumptions!C11+Assumptions!C12))*(1-Assumptions!C20))/Assumptions!C25 | O21: =(((Assumptions!D25*(Assumptions!D10*(1+Assumptions!D26)^(5-1)))*(Assumptions!D11+Assumptions!D12))*(1-Assumptions!D20))/Assumptions!D25 | P21: =(((Assumptions!E25*(Assumptions!E10*(1+Assumptions!E26)^(5-1)))*(Assumptions!E11+Assumptions!E12))*(1-Assumptions!E20))/Assumptions!E25
A22: Contribution after CAC per booking ($) | B22: =(((((Assumptions!C21*(Assumptions!C10*(1+Assumptions!C26)^(1-1)))*(Assumptions!C11+Assumptions!C12))*(1-Assumptions!C20))-((IF(Assumptions!C17=1,(((Assumptions!C21*(Assumptions!C10*(1+Assumptions!C26)^(1-1)))*(Assumptions!C11+Assumptions!C12))*(1-Assumptions!C20))*Assumptions!C15+Assumptions!C21*Assumptions!C16,(Assumptions!C21*(Assumptions!C10*(1+Assumptions!C26)^(1-1)))*Assumptions!C15+Assumptions!C21*Assumptions!C16))+((Assumptions!C21*(Assumptions!C10*(1+Assumptions!C26)^(1-1)))*Assumptions!C18)+(Assumptions!C21*Assumptions!C19)))-(Assumptions!C21*(Assumptions!C28+(Assumptions!C29-Assumptions!C28)*(1-1)/4)*Assumptions!C27))/Assumptions!C21 | C22: =(((((Assumptions!D21*(Assumptions!D10*(1+Assumptions!D26)^(1-1)))*(Assumptions!D11+Assumptions!D12))*(1-Assumptions!D20))-((IF(Assumptions!D17=1,(((Assumptions!D21*(Assumptions!D10*(1+Assumptions!D26)^(1-1)))*(Assumptions!D11+Assumptions!D12))*(1-Assumptions!D20))*Assumptions!D15+Assumptions!D21*Assumptions!D16,(Assumptions!D21*(Assumptions!D10*(1+Assumptions!D26)^(1-1)))*Assumptions!D15+Assumptions!D21*Assumptions!D16))+((Assumptions!D21*(Assumptions!D10*(1+Assumptions!D26)^(1-1)))*Assumptions!D18)+(Assumptions!D21*Assumptions!D19)))-(Assumptions!D21*(Assumptions!D28+(Assumptions!D29-Assumptions!D28)*(1-1)/4)*Assumptions!D27))/Assumptions!D21 | D22: =(((((Assumptions!E21*(Assumptions!E10*(1+Assumptions!E26)^(1-1)))*(Assumptions!E11+Assumptions!E12))*(1-Assumptions!E20))-((IF(Assumptions!E17=1,(((Assumptions!E21*(Assumptions!E10*(1+Assumptions!E26)^(1-1)))*(Assumptions!E11+Assumptions!E12))*(1-Assumptions!E20))*Assumptions!E15+Assumptions!E21*Assumptions!E16,(Assumptions!E21*(Assumptions!E10*(1+Assumptions!E26)^(1-1)))*Assumptions!E15+Assumptions!E21*Assumptions!E16))+((Assumptions!E21*(Assumptions!E10*(1+Assumptions!E26)^(1-1)))*Assumptions!E18)+(Assumptions!E21*Assumptions!E19)))-(Assumptions!E21*(Assumptions!E28+(Assumptions!E29-Assumptions!E28)*(1-1)/4)*Assumptions!E27))/Assumptions!E21 | E22: =(((((Assumptions!C22*(Assumptions!C10*(1+Assumptions!C26)^(2-1)))*(Assumptions!C11+Assumptions!C12))*(1-Assumptions!C20))-((IF(Assumptions!C17=1,(((Assumptions!C22*(Assumptions!C10*(1+Assumptions!C26)^(2-1)))*(Assumptions!C11+Assumptions!C12))*(1-Assumptions!C20))*Assumptions!C15+Assumptions!C22*Assumptions!C16,(Assumptions!C22*(Assumptions!C10*(1+Assumptions!C26)^(2-1)))*Assumptions!C15+Assumptions!C22*Assumptions!C16))+((Assumptions!C22*(Assumptions!C10*(1+Assumptions!C26)^(2-1)))*Assumptions!C18)+(Assumptions!C22*Assumptions!C19)))-(Assumptions!C22*(Assumptions!C28+(Assumptions!C29-Assumptions!C28)*(2-1)/4)*Assumptions!C27))/Assumptions!C22 | F22: =(((((Assumptions!D22*(Assumptions!D10*(1+Assumptions!D26)^(2-1)))*(Assumptions!D11+Assumptions!D12))*(1-Assumptions!D20))-((IF(Assumptions!D17=1,(((Assumptions!D22*(Assumptions!D10*(1+Assumptions!D26)^(2-1)))*(Assumptions!D11+Assumptions!D12))*(1-Assumptions!D20))*Assumptions!D15+Assumptions!D22*Assumptions!D16,(Assumptions!D22*(Assumptions!D10*(1+Assumptions!D26)^(2-1)))*Assumptions!D15+Assumptions!D22*Assumptions!D16))+((Assumptions!D22*(Assumptions!D10*(1+Assumptions!D26)^(2-1)))*Assumptions!D18)+(Assumptions!D22*Assumptions!D19)))-(Assumptions!D22*(Assumptions!D28+(Assumptions!D29-Assumptions!D28)*(2-1)/4)*Assumptions!D27))/Assumptions!D22 | G22: =(((((Assumptions!E22*(Assumptions!E10*(1+Assumptions!E26)^(2-1)))*(Assumptions!E11+Assumptions!E12))*(1-Assumptions!E20))-((IF(Assumptions!E17=1,(((Assumptions!E22*(Assumptions!E10*(1+Assumptions!E26)^(2-1)))*(Assumptions!E11+Assumptions!E12))*(1-Assumptions!E20))*Assumptions!E15+Assumptions!E22*Assumptions!E16,(Assumptions!E22*(Assumptions!E10*(1+Assumptions!E26)^(2-1)))*Assumptions!E15+Assumptions!E22*Assumptions!E16))+((Assumptions!E22*(Assumptions!E10*(1+Assumptions!E26)^(2-1)))*Assumptions!E18)+(Assumptions!E22*Assumptions!E19)))-(Assumptions!E22*(Assumptions!E28+(Assumptions!E29-Assumptions!E28)*(2-1)/4)*Assumptions!E27))/Assumptions!E22 | H22: =(((((Assumptions!C23*(Assumptions!C10*(1+Assumptions!C26)^(3-1)))*(Assumptions!C11+Assumptions!C12))*(1-Assumptions!C20))-((IF(Assumptions!C17=1,(((Assumptions!C23*(Assumptions!C10*(1+Assumptions!C26)^(3-1)))*(Assumptions!C11+Assumptions!C12))*(1-Assumptions!C20))*Assumptions!C15+Assumptions!C23*Assumptions!C16,(Assumptions!C23*(Assumptions!C10*(1+Assumptions!C26)^(3-1)))*Assumptions!C15+Assumptions!C23*Assumptions!C16))+((Assumptions!C23*(Assumptions!C10*(1+Assumptions!C26)^(3-1)))*Assumptions!C18)+(Assumptions!C23*Assumptions!C19)))-(Assumptions!C23*(Assumptions!C28+(Assumptions!C29-Assumptions!C28)*(3-1)/4)*Assumptions!C27))/Assumptions!C23 | I22: =(((((Assumptions!D23*(Assumptions!D10*(1+Assumptions!D26)^(3-1)))*(Assumptions!D11+Assumptions!D12))*(1-Assumptions!D20))-((IF(Assumptions!D17=1,(((Assumptions!D23*(Assumptions!D10*(1+Assumptions!D26)^(3-1)))*(Assumptions!D11+Assumptions!D12))*(1-Assumptions!D20))*Assumptions!D15+Assumptions!D23*Assumptions!D16,(Assumptions!D23*(Assumptions!D10*(1+Assumptions!D26)^(3-1)))*Assumptions!D15+Assumptions!D23*Assumptions!D16))+((Assumptions!D23*(Assumptions!D10*(1+Assumptions!D26)^(3-1)))*Assumptions!D18)+(Assumptions!D23*Assumptions!D19)))-(Assumptions!D23*(Assumptions!D28+(Assumptions!D29-Assumptions!D28)*(3-1)/4)*Assumptions!D27))/Assumptions!D23 | J22: =(((((Assumptions!E23*(Assumptions!E10*(1+Assumptions!E26)^(3-1)))*(Assumptions!E11+Assumptions!E12))*(1-Assumptions!E20))-((IF(Assumptions!E17=1,(((Assumptions!E23*(Assumptions!E10*(1+Assumptions!E26)^(3-1)))*(Assumptions!E11+Assumptions!E12))*(1-Assumptions!E20))*Assumptions!E15+Assumptions!E23*Assumptions!E16,(Assumptions!E23*(Assumptions!E10*(1+Assumptions!E26)^(3-1)))*Assumptions!E15+Assumptions!E23*Assumptions!E16))+((Assumptions!E23*(Assumptions!E10*(1+Assumptions!E26)^(3-1)))*Assumptions!E18)+(Assumptions!E23*Assumptions!E19)))-(Assumptions!E23*(Assumptions!E28+(Assumptions!E29-Assumptions!E28)*(3-1)/4)*Assumptions!E27))/Assumptions!E23 | K22: =(((((Assumptions!C24*(Assumptions!C10*(1+Assumptions!C26)^(4-1)))*(Assumptions!C11+Assumptions!C12))*(1-Assumptions!C20))-((IF(Assumptions!C17=1,(((Assumptions!C24*(Assumptions!C10*(1+Assumptions!C26)^(4-1)))*(Assumptions!C11+Assumptions!C12))*(1-Assumptions!C20))*Assumptions!C15+Assumptions!C24*Assumptions!C16,(Assumptions!C24*(Assumptions!C10*(1+Assumptions!C26)^(4-1)))*Assumptions!C15+Assumptions!C24*Assumptions!C16))+((Assumptions!C24*(Assumptions!C10*(1+Assumptions!C26)^(4-1)))*Assumptions!C18)+(Assumptions!C24*Assumptions!C19)))-(Assumptions!C24*(Assumptions!C28+(Assumptions!C29-Assumptions!C28)*(4-1)/4)*Assumptions!C27))/Assumptions!C24 | L22: =(((((Assumptions!D24*(Assumptions!D10*(1+Assumptions!D26)^(4-1)))*(Assumptions!D11+Assumptions!D12))*(1-Assumptions!D20))-((IF(Assumptions!D17=1,(((Assumptions!D24*(Assumptions!D10*(1+Assumptions!D26)^(4-1)))*(Assumptions!D11+Assumptions!D12))*(1-Assumptions!D20))*Assumptions!D15+Assumptions!D24*Assumptions!D16,(Assumptions!D24*(Assumptions!D10*(1+Assumptions!D26)^(4-1)))*Assumptions!D15+Assumptions!D24*Assumptions!D16))+((Assumptions!D24*(Assumptions!D10*(1+Assumptions!D26)^(4-1)))*Assumptions!D18)+(Assumptions!D24*Assumptions!D19)))-(Assumptions!D24*(Assumptions!D28+(Assumptions!D29-Assumptions!D28)*(4-1)/4)*Assumptions!D27))/Assumptions!D24 | M22: =(((((Assumptions!E24*(Assumptions!E10*(1+Assumptions!E26)^(4-1)))*(Assumptions!E11+Assumptions!E12))*(1-Assumptions!E20))-((IF(Assumptions!E17=1,(((Assumptions!E24*(Assumptions!E10*(1+Assumptions!E26)^(4-1)))*(Assumptions!E11+Assumptions!E12))*(1-Assumptions!E20))*Assumptions!E15+Assumptions!E24*Assumptions!E16,(Assumptions!E24*(Assumptions!E10*(1+Assumptions!E26)^(4-1)))*Assumptions!E15+Assumptions!E24*Assumptions!E16))+((Assumptions!E24*(Assumptions!E10*(1+Assumptions!E26)^(4-1)))*Assumptions!E18)+(Assumptions!E24*Assumptions!E19)))-(Assumptions!E24*(Assumptions!E28+(Assumptions!E29-Assumptions!E28)*(4-1)/4)*Assumptions!E27))/Assumptions!E24 | N22: =(((((Assumptions!C25*(Assumptions!C10*(1+Assumptions!C26)^(5-1)))*(Assumptions!C11+Assumptions!C12))*(1-Assumptions!C20))-((IF(Assumptions!C17=1,(((Assumptions!C25*(Assumptions!C10*(1+Assumptions!C26)^(5-1)))*(Assumptions!C11+Assumptions!C12))*(1-Assumptions!C20))*Assumptions!C15+Assumptions!C25*Assumptions!C16,(Assumptions!C25*(Assumptions!C10*(1+Assumptions!C26)^(5-1)))*Assumptions!C15+Assumptions!C25*Assumptions!C16))+((Assumptions!C25*(Assumptions!C10*(1+Assumptions!C26)^(5-1)))*Assumptions!C18)+(Assumptions!C25*Assumptions!C19)))-(Assumptions!C25*(Assumptions!C28+(Assumptions!C29-Assumptions!C28)*(5-1)/4)*Assumptions!C27))/Assumptions!C25 | O22: =(((((Assumptions!D25*(Assumptions!D10*(1+Assumptions!D26)^(5-1)))*(Assumptions!D11+Assumptions!D12))*(1-Assumptions!D20))-((IF(Assumptions!D17=1,(((Assumptions!D25*(Assumptions!D10*(1+Assumptions!D26)^(5-1)))*(Assumptions!D11+Assumptions!D12))*(1-Assumptions!D20))*Assumptions!D15+Assumptions!D25*Assumptions!D16,(Assumptions!D25*(Assumptions!D10*(1+Assumptions!D26)^(5-1)))*Assumptions!D15+Assumptions!D25*Assumptions!D16))+((Assumptions!D25*(Assumptions!D10*(1+Assumptions!D26)^(5-1)))*Assumptions!D18)+(Assumptions!D25*Assumptions!D19)))-(Assumptions!D25*(Assumptions!D28+(Assumptions!D29-Assumptions!D28)*(5-1)/4)*Assumptions!D27))/Assumptions!D25 | P22: =(((((Assumptions!E25*(Assumptions!E10*(1+Assumptions!E26)^(5-1)))*(Assumptions!E11+Assumptions!E12))*(1-Assumptions!E20))-((IF(Assumptions!E17=1,(((Assumptions!E25*(Assumptions!E10*(1+Assumptions!E26)^(5-1)))*(Assumptions!E11+Assumptions!E12))*(1-Assumptions!E20))*Assumptions!E15+Assumptions!E25*Assumptions!E16,(Assumptions!E25*(Assumptions!E10*(1+Assumptions!E26)^(5-1)))*Assumptions!E15+Assumptions!E25*Assumptions!E16))+((Assumptions!E25*(Assumptions!E10*(1+Assumptions!E26)^(5-1)))*Assumptions!E18)+(Assumptions!E25*Assumptions!E19)))-(Assumptions!E25*(Assumptions!E28+(Assumptions!E29-Assumptions!E28)*(5-1)/4)*Assumptions!E27))/Assumptions!E25
A24: SELECTED SCENARIO SUMMARY (Assumptions!C5)
A25: Active scenario | B25: =Assumptions!C5
A26: Year | B26: Bookings | C26: GMV | D26: Revenue (after drag) | E26: Net profit
A27: 1 | B27: =IF($B$25="Conservative",B5,IF($B$25="Upside",D5,C5)) | C27: =IF($B$25="Conservative",B7,IF($B$25="Upside",D7,C7)) | D27: =IF($B$25="Conservative",B10,IF($B$25="Upside",D10,C10)) | E27: =IF($B$25="Conservative",B19,IF($B$25="Upside",D19,C19))
A28: 2 | B28: =IF($B$25="Conservative",E5,IF($B$25="Upside",G5,F5)) | C28: =IF($B$25="Conservative",E7,IF($B$25="Upside",G7,F7)) | D28: =IF($B$25="Conservative",E10,IF($B$25="Upside",G10,F10)) | E28: =IF($B$25="Conservative",E19,IF($B$25="Upside",G19,F19))
A29: 3 | B29: =IF($B$25="Conservative",H5,IF($B$25="Upside",J5,I5)) | C29: =IF($B$25="Conservative",H7,IF($B$25="Upside",J7,I7)) | D29: =IF($B$25="Conservative",H10,IF($B$25="Upside",J10,I10)) | E29: =IF($B$25="Conservative",H19,IF($B$25="Upside",J19,I19))
A30: 4 | B30: =IF($B$25="Conservative",K5,IF($B$25="Upside",M5,L5)) | C30: =IF($B$25="Conservative",K7,IF($B$25="Upside",M7,L7)) | D30: =IF($B$25="Conservative",K10,IF($B$25="Upside",M10,L10)) | E30: =IF($B$25="Conservative",K19,IF($B$25="Upside",M19,L19))
A31: 5 | B31: =IF($B$25="Conservative",N5,IF($B$25="Upside",P5,O5)) | C31: =IF($B$25="Conservative",N7,IF($B$25="Upside",P7,O7)) | D31: =IF($B$25="Conservative",N10,IF($B$25="Upside",P10,O10)) | E31: =IF($B$25="Conservative",N19,IF($B$25="Upside",P19,O19))
A33: Operator payout ~(1−take)×GMV excluded from GCCN costs (marketplace). Y1 OTA share = 0 in Base.
A34: Point estimates; BUSINESS_PLAN_5YR.md states sensitivity ranges around Base Y1 and Y5.

Sheet Monthly_Y1
A1: GCCN Year 1 Monthly — Seasonality
A2: Weights ASSUMPTION shaped by sourced ~70% lodging tax Apr–Sep. Edit yellow; must sum 100%.
A4: Month | B4: Season_Weight (INPUT) | C4: Cons Bookings | D4: Base Bookings | E4: Upside Bookings | F4: Cons GMV | G4: Base GMV | H4: Upside GMV | I4: Cons Plat. Rev* | J4: Base Plat. Rev* | K4: Upside Plat. Rev* | L4: Notes
A5: Jan | B5: 0.03 | C5: =Assumptions!C21*B5 | D5: =Assumptions!D21*B5 | E5: =Assumptions!E21*B5 | F5: =C5*Assumptions!C10 | G5: =D5*Assumptions!D10 | H5: =E5*Assumptions!E10 | I5: =F5*(Assumptions!C11+Assumptions!C12)*(1-Assumptions!C20) | J5: =G5*(Assumptions!D11+Assumptions!D12)*(1-Assumptions!D20) | K5: =H5*(Assumptions!E11+Assumptions!E12)*(1-Assumptions!E20) | L5: Trough
A6: Feb | B6: 0.03 | C6: =Assumptions!C21*B6 | D6: =Assumptions!D21*B6 | E6: =Assumptions!E21*B6 | F6: =C6*Assumptions!C10 | G6: =D6*Assumptions!D10 | H6: =E6*Assumptions!E10 | I6: =F6*(Assumptions!C11+Assumptions!C12)*(1-Assumptions!C20) | J6: =G6*(Assumptions!D11+Assumptions!D12)*(1-Assumptions!D20) | K6: =H6*(Assumptions!E11+Assumptions!E12)*(1-Assumptions!E20) | L6: Trough
A7: Mar | B7: 0.06 | C7: =Assumptions!C21*B7 | D7: =Assumptions!D21*B7 | E7: =Assumptions!E21*B7 | F7: =C7*Assumptions!C10 | G7: =D7*Assumptions!D10 | H7: =E7*Assumptions!E10 | I7: =F7*(Assumptions!C11+Assumptions!C12)*(1-Assumptions!C20) | J7: =G7*(Assumptions!D11+Assumptions!D12)*(1-Assumptions!D20) | K7: =H7*(Assumptions!E11+Assumptions!E12)*(1-Assumptions!E20) | L7: Build
A8: Apr | B8: 0.08 | C8: =Assumptions!C21*B8 | D8: =Assumptions!D21*B8 | E8: =Assumptions!E21*B8 | F8: =C8*Assumptions!C10 | G8: =D8*Assumptions!D10 | H8: =E8*Assumptions!E10 | I8: =F8*(Assumptions!C11+Assumptions!C12)*(1-Assumptions!C20) | J8: =G8*(Assumptions!D11+Assumptions!D12)*(1-Assumptions!D20) | K8: =H8*(Assumptions!E11+Assumptions!E12)*(1-Assumptions!E20) | L8: Shoulder
A9: May | B9: 0.1 | C9: =Assumptions!C21*B9 | D9: =Assumptions!D21*B9 | E9: =Assumptions!E21*B9 | F9: =C9*Assumptions!C10 | G9: =D9*Assumptions!D10 | H9: =E9*Assumptions!E10 | I9: =F9*(Assumptions!C11+Assumptions!C12)*(1-Assumptions!C20) | J9: =G9*(Assumptions!D11+Assumptions!D12)*(1-Assumptions!D20) | K9: =H9*(Assumptions!E11+Assumptions!E12)*(1-Assumptions!E20) | L9: Shoulder
A10: Jun | B10: 0.14 | C10: =Assumptions!C21*B10 | D10: =Assumptions!D21*B10 | E10: =Assumptions!E21*B10 | F10: =C10*Assumptions!C10 | G10: =D10*Assumptions!D10 | H10: =E10*Assumptions!E10 | I10: =F10*(Assumptions!C11+Assumptions!C12)*(1-Assumptions!C20) | J10: =G10*(Assumptions!D11+Assumptions!D12)*(1-Assumptions!D20) | K10: =H10*(Assumptions!E11+Assumptions!E12)*(1-Assumptions!E20) | L10: Peak
A11: Jul | B11: 0.15 | C11: =Assumptions!C21*B11 | D11: =Assumptions!D21*B11 | E11: =Assumptions!E21*B11 | F11: =C11*Assumptions!C10 | G11: =D11*Assumptions!D10 | H11: =E11*Assumptions!E10 | I11: =F11*(Assumptions!C11+Assumptions!C12)*(1-Assumptions!C20) | J11: =G11*(Assumptions!D11+Assumptions!D12)*(1-Assumptions!D20) | K11: =H11*(Assumptions!E11+Assumptions!E12)*(1-Assumptions!E20) | L11: Peak
A12: Aug | B12: 0.14 | C12: =Assumptions!C21*B12 | D12: =Assumptions!D21*B12 | E12: =Assumptions!E21*B12 | F12: =C12*Assumptions!C10 | G12: =D12*Assumptions!D10 | H12: =E12*Assumptions!E10 | I12: =F12*(Assumptions!C11+Assumptions!C12)*(1-Assumptions!C20) | J12: =G12*(Assumptions!D11+Assumptions!D12)*(1-Assumptions!D20) | K12: =H12*(Assumptions!E11+Assumptions!E12)*(1-Assumptions!E20) | L12: Peak
A13: Sep | B13: 0.09 | C13: =Assumptions!C21*B13 | D13: =Assumptions!D21*B13 | E13: =Assumptions!E21*B13 | F13: =C13*Assumptions!C10 | G13: =D13*Assumptions!D10 | H13: =E13*Assumptions!E10 | I13: =F13*(Assumptions!C11+Assumptions!C12)*(1-Assumptions!C20) | J13: =G13*(Assumptions!D11+Assumptions!D12)*(1-Assumptions!D20) | K13: =H13*(Assumptions!E11+Assumptions!E12)*(1-Assumptions!E20) | L13: Shoulder
A14: Oct | B14: 0.08 | C14: =Assumptions!C21*B14 | D14: =Assumptions!D21*B14 | E14: =Assumptions!E21*B14 | F14: =C14*Assumptions!C10 | G14: =D14*Assumptions!D10 | H14: =E14*Assumptions!E10 | I14: =F14*(Assumptions!C11+Assumptions!C12)*(1-Assumptions!C20) | J14: =G14*(Assumptions!D11+Assumptions!D12)*(1-Assumptions!D20) | K14: =H14*(Assumptions!E11+Assumptions!E12)*(1-Assumptions!E20) | L14: Shoulder
A15: Nov | B15: 0.05 | C15: =Assumptions!C21*B15 | D15: =Assumptions!D21*B15 | E15: =Assumptions!E21*B15 | F15: =C15*Assumptions!C10 | G15: =D15*Assumptions!D10 | H15: =E15*Assumptions!E10 | I15: =F15*(Assumptions!C11+Assumptions!C12)*(1-Assumptions!C20) | J15: =G15*(Assumptions!D11+Assumptions!D12)*(1-Assumptions!D20) | K15: =H15*(Assumptions!E11+Assumptions!E12)*(1-Assumptions!E20) | L15: Trough
A16: Dec | B16: 0.05 | C16: =Assumptions!C21*B16 | D16: =Assumptions!D21*B16 | E16: =Assumptions!E21*B16 | F16: =C16*Assumptions!C10 | G16: =D16*Assumptions!D10 | H16: =E16*Assumptions!E10 | I16: =F16*(Assumptions!C11+Assumptions!C12)*(1-Assumptions!C20) | J16: =G16*(Assumptions!D11+Assumptions!D12)*(1-Assumptions!D20) | K16: =H16*(Assumptions!E11+Assumptions!E12)*(1-Assumptions!E20) | L16: Trough
A17: TOTAL | B17: =SUM(B5:B16) | C17: =SUM(C5:C16) | D17: =SUM(D5:D16) | E17: =SUM(E5:E16) | F17: =SUM(F5:F16) | G17: =SUM(G5:G16) | H17: =SUM(H5:H16) | I17: =SUM(I5:I16) | ... K17: =SUM(K5:K16)
A19: * Platform Rev = GMV × effective take × (1 − weather drag).
A20: Apr–Sep weight sum: | B20: =SUM(B8:B13) | C20: Near sourced ~70% lodging seasonality (ASSUMPTION for charter shape).

Sheet Unit_Economics
A1: GCCN Unit Economics — Per Completed Booking (Y1)
A2: Contribution after variable COGS and blended paid CAC. Operator receipt is partner-side.
A4: Line item | B4: Conservative | C4: Base | D4: Upside | E4: Notes
A5: AOV | B5: =Assumptions!C10 | C5: =Assumptions!D10 | D5: =Assumptions!E10 | E5: U1
A6: Effective take rate | B6: =(Assumptions!C11+Assumptions!C12) | C6: =(Assumptions!D11+Assumptions!D12) | D6: =(Assumptions!E11+Assumptions!E12) | E6: U2+U3
A7: Gross take $ | B7: =(Assumptions!C10*(Assumptions!C11+Assumptions!C12)) | C7: =(Assumptions!D10*(Assumptions!D11+Assumptions!D12)) | D7: =(Assumptions!E10*(Assumptions!E11+Assumptions!E12)) | E7: AOV×take
A8: Weather drag $ | B8: =((Assumptions!C10*(Assumptions!C11+Assumptions!C12))*Assumptions!C20) | C8: =((Assumptions!D10*(Assumptions!D11+Assumptions!D12))*Assumptions!D20) | D8: =((Assumptions!E10*(Assumptions!E11+Assumptions!E12))*Assumptions!E20) | E8: gross×U11
A9: Net take $ (platform revenue) | B9: =((Assumptions!C10*(Assumptions!C11+Assumptions!C12))*(1-Assumptions!C20)) | C9: =((Assumptions!D10*(Assumptions!D11+Assumptions!D12))*(1-Assumptions!D20)) | D9: =((Assumptions!E10*(Assumptions!E11+Assumptions!E12))*(1-Assumptions!E20)) | E9: primary unit revenue
A10: Stripe fees $ (fee-slice) | B10: =(IF(Assumptions!C17=1,((Assumptions!C10*(Assumptions!C11+Assumptions!C12))*(1-Assumptions!C20))*Assumptions!C15+Assumptions!C16,Assumptions!C10*Assumptions!C15+Assumptions!C16)) | C10: =(IF(Assumptions!D17=1,((Assumptions!D10*(Assumptions!D11+Assumptions!D12))*(1-Assumptions!D20))*Assumptions!D15+Assumptions!D16,Assumptions!D10*Assumptions!D15+Assumptions!D16)) | D10: =(IF(Assumptions!E17=1,((Assumptions!E10*(Assumptions!E11+Assumptions!E12))*(1-Assumptions!E20))*Assumptions!E15+Assumptions!E16,Assumptions!E10*Assumptions!E15+Assumptions!E16)) | E10: U8=1 recommended
A11: Referral credit $ | B11: =(Assumptions!C10*Assumptions!C18) | C11: =(Assumptions!D10*Assumptions!D18) | D11: =(Assumptions!E10*Assumptions!E18) | E11: blended U9
A12: SMS/email $ | B12: =Assumptions!C19 | C12: =Assumptions!D19 | D12: =Assumptions!E19 | E12: U10
A13: Variable COGS $ | B13: =((IF(Assumptions!C17=1,((Assumptions!C10*(Assumptions!C11+Assumptions!C12))*(1-Assumptions!C20))*Assumptions!C15+Assumptions!C16,Assumptions!C10*Assumptions!C15+Assumptions!C16))+(Assumptions!C10*Assumptions!C18)+Assumptions!C19) | C13: =((IF(Assumptions!D17=1,((Assumptions!D10*(Assumptions!D11+Assumptions!D12))*(1-Assumptions!D20))*Assumptions!D15+Assumptions!D16,Assumptions!D10*Assumptions!D15+Assumptions!D16))+(Assumptions!D10*Assumptions!D18)+Assumptions!D19) | D13: =((IF(Assumptions!E17=1,((Assumptions!E10*(Assumptions!E11+Assumptions!E12))*(1-Assumptions!E20))*Assumptions!E15+Assumptions!E16,Assumptions!E10*Assumptions!E15+Assumptions!E16))+(Assumptions!E10*Assumptions!E18)+Assumptions!E19) | E13: sum
A14: Contribution before CAC $ | B14: =(((Assumptions!C10*(Assumptions!C11+Assumptions!C12))*(1-Assumptions!C20))-((IF(Assumptions!C17=1,((Assumptions!C10*(Assumptions!C11+Assumptions!C12))*(1-Assumptions!C20))*Assumptions!C15+Assumptions!C16,Assumptions!C10*Assumptions!C15+Assumptions!C16))+(Assumptions!C10*Assumptions!C18)+Assumptions!C19)) | C14: =(((Assumptions!D10*(Assumptions!D11+Assumptions!D12))*(1-Assumptions!D20))-((IF(Assumptions!D17=1,((Assumptions!D10*(Assumptions!D11+Assumptions!D12))*(1-Assumptions!D20))*Assumptions!D15+Assumptions!D16,Assumptions!D10*Assumptions!D15+Assumptions!D16))+(Assumptions!D10*Assumptions!D18)+Assumptions!D19)) | D14: =(((Assumptions!E10*(Assumptions!E11+Assumptions!E12))*(1-Assumptions!E20))-((IF(Assumptions!E17=1,((Assumptions!E10*(Assumptions!E11+Assumptions!E12))*(1-Assumptions!E20))*Assumptions!E15+Assumptions!E16,Assumptions!E10*Assumptions!E15+Assumptions!E16))+(Assumptions!E10*Assumptions!E18)+Assumptions!E19)) | E14: net−COGS
A15: Blended paid CAC $ (Y1) | B15: =(Assumptions!C27*Assumptions!C28) | C15: =(Assumptions!D27*Assumptions!D28) | D15: =(Assumptions!E27*Assumptions!E28) | E15: C1×C2
A16: Contribution after blended CAC $ | B16: =((((Assumptions!C10*(Assumptions!C11+Assumptions!C12))*(1-Assumptions!C20))-((IF(Assumptions!C17=1,((Assumptions!C10*(Assumptions!C11+Assumptions!C12))*(1-Assumptions!C20))*Assumptions!C15+Assumptions!C16,Assumptions!C10*Assumptions!C15+Assumptions!C16))+(Assumptions!C10*Assumptions!C18)+Assumptions!C19))-(Assumptions!C27*Assumptions!C28)) | C16: =((((Assumptions!D10*(Assumptions!D11+Assumptions!D12))*(1-Assumptions!D20))-((IF(Assumptions!D17=1,((Assumptions!D10*(Assumptions!D11+Assumptions!D12))*(1-Assumptions!D20))*Assumptions!D15+Assumptions!D16,Assumptions!D10*Assumptions!D15+Assumptions!D16))+(Assumptions!D10*Assumptions!D18)+Assumptions!D19))-(Assumptions!D27*Assumptions!D28)) | D16: =((((Assumptions!E10*(Assumptions!E11+Assumptions!E12))*(1-Assumptions!E20))-((IF(Assumptions!E17=1,((Assumptions!E10*(Assumptions!E11+Assumptions!E12))*(1-Assumptions!E20))*Assumptions!E15+Assumptions!E16,Assumptions!E10*Assumptions!E15+Assumptions!E16))+(Assumptions!E10*Assumptions!E18)+Assumptions!E19))-(Assumptions!E27*Assumptions!E28)) | E16: KEY METRIC
A17: Deposit at book $ | B17: =(Assumptions!C10*Assumptions!C14) | C17: =(Assumptions!D10*Assumptions!D14) | D17: =(Assumptions!E10*Assumptions!E14) | E17: cash U5
A18: Implied operator receipt $ | B18: =(Assumptions!C10*(1-(Assumptions!C11+Assumptions!C12))) | C18: =(Assumptions!D10*(1-(Assumptions!D11+Assumptions!D12))) | D18: =(Assumptions!E10*(1-(Assumptions!E11+Assumptions!E12))) | E18: partner ~(1−take)×AOV
A20: External fee benchmarks (context)
A21: FareHarbor typical booking fee | B21: 0.06 | C21: SOURCED ~5-8%, often ~6%
A22: FareHarbor OTA API fee addl. | B22: 0.02 | C22: SOURCED ~2%
A23: Viator/GYG typical commission | B23: 0.25 | C23: SOURCED ~20-30%
A24: GCCN Base effective take | B24: =Assumptions!D11+Assumptions!D12 | C24: ASSUMPTION owned Stripe
